{
    "DataList": [
       {
   "TBL_ID": "DT_NSO_1001_021V1",
   "Period": 2019,
   "CODE": 18101,
   "SCR_MN": "Улиастай",
   "SCR_ENG": "Uliastai",
   "CODE1": 1,
   "SCR_MN1": "Бүгд",
   "SCR_ENG1": "Total",
   "CODE2": "",
   "SCR_MN2": "",
   "SCR_ENG2": "",
   "DTVAL_CO": 154001
 },
 {
   "TBL_ID": "DT_NSO_1001_021V1",
   "Period": 2019,
   "CODE": 18104,
   "SCR_MN": "Алдархаан",
   "SCR_ENG": "Aldarkhaan",
   "CODE1": 1,
   "SCR_MN1": "Бүгд",
   "SCR_ENG1": "Total",
   "CODE2": "",
   "SCR_MN2": "",
   "SCR_ENG2": "",
   "DTVAL_CO": 316100
 },
 {
   "TBL_ID": "DT_NSO_1001_021V1",
   "Period": 2019,
   "CODE": 18107,
   "SCR_MN": "Асгат",
   "SCR_ENG": "Asgat",
   "CODE1": 1,
   "SCR_MN1": "Бүгд",
   "SCR_ENG1": "Total",
   "CODE2": "",
   "SCR_MN2": "",
   "SCR_ENG2": "",
   "DTVAL_CO": 52892
 },
 {
   "TBL_ID": "DT_NSO_1001_021V1",
   "Period": 2019,
   "CODE": 18110,
   "SCR_MN": "Баянтэс",
   "SCR_ENG": "Bayantes",
   "CODE1": 1,
   "SCR_MN1": "Бүгд",
   "SCR_ENG1": "Total",
   "CODE2": "",
   "SCR_MN2": "",
   "SCR_ENG2": "",
   "DTVAL_CO": 180688
 },
 {
   "TBL_ID": "DT_NSO_1001_021V1",
   "Period": 2019,
   "CODE": 18113,
   "SCR_MN": "Баянхайрхан",
   "SCR_ENG": "Bayankhairkhan",
   "CODE1": 1,
   "SCR_MN1": "Бүгд",
   "SCR_ENG1": "Total",
   "CODE2": "",
   "SCR_MN2": "",
   "SCR_ENG2": "",
   "DTVAL_CO": 130243
 },
 {
   "TBL_ID": "DT_NSO_1001_021V1",
   "Period": 2019,
   "CODE": 18116,
   "SCR_MN": "Дөрвөлжин",
   "SCR_ENG": "Durvuljin",
   "CODE1": 1,
   "SCR_MN1": "Бүгд",
   "SCR_ENG1": "Total",
   "CODE2": "",
   "SCR_MN2": "",
   "SCR_ENG2": "",
   "DTVAL_CO": 170936
 },
 {
   "TBL_ID": "DT_NSO_1001_021V1",
   "Period": 2019,
   "CODE": 18119,
   "SCR_MN": "Завханмандал",
   "SCR_ENG": "Zavkhanmandal",
   "CODE1": 1,
   "SCR_MN1": "Бүгд",
   "SCR_ENG1": "Total",
   "CODE2": "",
   "SCR_MN2": "",
   "SCR_ENG2": "",
   "DTVAL_CO": 97415
 },
 {
   "TBL_ID": "DT_NSO_1001_021V1",
   "Period": 2019,
   "CODE": 18122,
   "SCR_MN": "Идэр",
   "SCR_ENG": "Ider",
   "CODE1": 1,
   "SCR_MN1": "Бүгд",
   "SCR_ENG1": "Total",
   "CODE2": "",
   "SCR_MN2": "",
   "SCR_ENG2": "",
   "DTVAL_CO": 123232
 },
 {
   "TBL_ID": "DT_NSO_1001_021V1",
   "Period": 2019,
   "CODE": 18125,
   "SCR_MN": "Их-Уул",
   "SCR_ENG": "Ikh-Uul",
   "CODE1": 1,
   "SCR_MN1": "Бүгд",
   "SCR_ENG1": "Total",
   "CODE2": "",
   "SCR_MN2": "",
   "SCR_ENG2": "",
   "DTVAL_CO": 289268
 },
 {
   "TBL_ID": "DT_NSO_1001_021V1",
   "Period": 2019,
   "CODE": 18128,
   "SCR_MN": "Нөмрөг",
   "SCR_ENG": "Numrug",
   "CODE1": 1,
   "SCR_MN1": "Бүгд",
   "SCR_ENG1": "Total",
   "CODE2": "",
   "SCR_MN2": "",
   "SCR_ENG2": "",
   "DTVAL_CO": 134706
 },
 {
   "TBL_ID": "DT_NSO_1001_021V1",
   "Period": 2019,
   "CODE": 18131,
   "SCR_MN": "Отгон",
   "SCR_ENG": "Otgon",
   "CODE1": 1,
   "SCR_MN1": "Бүгд",
   "SCR_ENG1": "Total",
   "CODE2": "",
   "SCR_MN2": "",
   "SCR_ENG2": "",
   "DTVAL_CO": 232539
 },
 {
   "TBL_ID": "DT_NSO_1001_021V1",
   "Period": 2019,
   "CODE": 18134,
   "SCR_MN": "Сантмаргац",
   "SCR_ENG": "Santmargats",
   "CODE1": 1,
   "SCR_MN1": "Бүгд",
   "SCR_ENG1": "Total",
   "CODE2": "",
   "SCR_MN2": "",
   "SCR_ENG2": "",
   "DTVAL_CO": 156914
 },
 {
   "TBL_ID": "DT_NSO_1001_021V1",
   "Period": 2019,
   "CODE": 18137,
   "SCR_MN": "Сонгино",
   "SCR_ENG": "Songino",
   "CODE1": 1,
   "SCR_MN1": "Бүгд",
   "SCR_ENG1": "Total",
   "CODE2": "",
   "SCR_MN2": "",
   "SCR_ENG2": "",
   "DTVAL_CO": 121128
 },
 {
   "TBL_ID": "DT_NSO_1001_021V1",
   "Period": 2019,
   "CODE": 18140,
   "SCR_MN": "Тосонцэнгэл",
   "SCR_ENG": "Tosontsengel",
   "CODE1": 1,
   "SCR_MN1": "Бүгд",
   "SCR_ENG1": "Total",
   "CODE2": "",
   "SCR_MN2": "",
   "SCR_ENG2": "",
   "DTVAL_CO": 196014
 },
 {
   "TBL_ID": "DT_NSO_1001_021V1",
   "Period": 2019,
   "CODE": 18143,
   "SCR_MN": "Түдэвтэй",
   "SCR_ENG": "Tudevtei",
   "CODE1": 1,
   "SCR_MN1": "Бүгд",
   "SCR_ENG1": "Total",
   "CODE2": "",
   "SCR_MN2": "",
   "SCR_ENG2": "",
   "DTVAL_CO": 133415
 },
 {
   "TBL_ID": "DT_NSO_1001_021V1",
   "Period": 2019,
   "CODE": 18146,
   "SCR_MN": "Тэлмэн",
   "SCR_ENG": "Telmen",
   "CODE1": 1,
   "SCR_MN1": "Бүгд",
   "SCR_ENG1": "Total",
   "CODE2": "",
   "SCR_MN2": "",
   "SCR_ENG2": "",
   "DTVAL_CO": 162419
 },
 {
   "TBL_ID": "DT_NSO_1001_021V1",
   "Period": 2019,
   "CODE": 18149,
   "SCR_MN": "Тэс",
   "SCR_ENG": "Tes",
   "CODE1": 1,
   "SCR_MN1": "Бүгд",
   "SCR_ENG1": "Total",
   "CODE2": "",
   "SCR_MN2": "",
   "SCR_ENG2": "",
   "DTVAL_CO": 115385
 },
 {
   "TBL_ID": "DT_NSO_1001_021V1",
   "Period": 2019,
   "CODE": 18152,
   "SCR_MN": "Ургамал",
   "SCR_ENG": "Urgamal",
   "CODE1": 1,
   "SCR_MN1": "Бүгд",
   "SCR_ENG1": "Total",
   "CODE2": "",
   "SCR_MN2": "",
   "SCR_ENG2": "",
   "DTVAL_CO": 109063
 },
 {
   "TBL_ID": "DT_NSO_1001_021V1",
   "Period": 2019,
   "CODE": 18155,
   "SCR_MN": "Цагаанхайрхан",
   "SCR_ENG": "Tsagaankhairkhan",
   "CODE1": 1,
   "SCR_MN1": "Бүгд",
   "SCR_ENG1": "Total",
   "CODE2": "",
   "SCR_MN2": "",
   "SCR_ENG2": "",
   "DTVAL_CO": 106682
 },
 {
   "TBL_ID": "DT_NSO_1001_021V1",
   "Period": 2019,
   "CODE": 18158,
   "SCR_MN": "Цагаанчулуут",
   "SCR_ENG": "Tsagaanchuluut",
   "CODE1": 1,
   "SCR_MN1": "Бүгд",
   "SCR_ENG1": "Total",
   "CODE2": "",
   "SCR_MN2": "",
   "SCR_ENG2": "",
   "DTVAL_CO": 111905
 },
 {
   "TBL_ID": "DT_NSO_1001_021V1",
   "Period": 2019,
   "CODE": 18161,
   "SCR_MN": "Цэцэн-Уул",
   "SCR_ENG": "Tsetsen-Uul",
   "CODE1": 1,
   "SCR_MN1": "Бүгд",
   "SCR_ENG1": "Total",
   "CODE2": "",
   "SCR_MN2": "",
   "SCR_ENG2": "",
   "DTVAL_CO": 168523
 },
 {
   "TBL_ID": "DT_NSO_1001_021V1",
   "Period": 2019,
   "CODE": 18164,
   "SCR_MN": "Шилүүстэй",
   "SCR_ENG": "Shiluustei",
   "CODE1": 1,
   "SCR_MN1": "Бүгд",
   "SCR_ENG1": "Total",
   "CODE2": "",
   "SCR_MN2": "",
   "SCR_ENG2": "",
   "DTVAL_CO": 141372
 },
 {
   "TBL_ID": "DT_NSO_1001_021V1",
   "Period": 2019,
   "CODE": 18167,
   "SCR_MN": "Эрдэнэхайрхан",
   "SCR_ENG": "Erdenekhairkhan",
   "CODE1": 1,
   "SCR_MN1": "Бүгд",
   "SCR_ENG1": "Total",
   "CODE2": "",
   "SCR_MN2": "",
   "SCR_ENG2": "",
   "DTVAL_CO": 219465
 },
 {
   "TBL_ID": "DT_NSO_1001_021V1",
   "Period": 2019,
   "CODE": 18170,
   "SCR_MN": "Яруу",
   "SCR_ENG": "Yaruu",
   "CODE1": 1,
   "SCR_MN1": "Бүгд",
   "SCR_ENG1": "Total",
   "CODE2": "",
   "SCR_MN2": "",
   "SCR_ENG2": "",
   "DTVAL_CO": 225601
 },
 {
   "TBL_ID": "DT_NSO_1001_021V1",
   "Period": 2019,
   "CODE": 18201,
   "SCR_MN": "Есөнбулаг",
   "SCR_ENG": "Yesunbulag",
   "CODE1": 1,
   "SCR_MN1": "Бүгд",
   "SCR_ENG1": "Total",
   "CODE2": "",
   "SCR_MN2": "",
   "SCR_ENG2": "",
   "DTVAL_CO": 232589
 },
 {
   "TBL_ID": "DT_NSO_1001_021V1",
   "Period": 2019,
   "CODE": 18204,
   "SCR_MN": "Алтай",
   "SCR_ENG": "Altai",
   "CODE1": 1,
   "SCR_MN1": "Бүгд",
   "SCR_ENG1": "Total",
   "CODE2": "",
   "SCR_MN2": "",
   "SCR_ENG2": "",
   "DTVAL_CO": 151367
 },
 {
   "TBL_ID": "DT_NSO_1001_021V1",
   "Period": 2019,
   "CODE": 18207,
   "SCR_MN": "Баян-Уул",
   "SCR_ENG": "Bayan-Uul",
   "CODE1": 1,
   "SCR_MN1": "Бүгд",
   "SCR_ENG1": "Total",
   "CODE2": "",
   "SCR_MN2": "",
   "SCR_ENG2": "",
   "DTVAL_CO": 192676
 },
 {
   "TBL_ID": "DT_NSO_1001_021V1",
   "Period": 2019,
   "CODE": 18210,
   "SCR_MN": "Бигэр",
   "SCR_ENG": "Biger",
   "CODE1": 1,
   "SCR_MN1": "Бүгд",
   "SCR_ENG1": "Total",
   "CODE2": "",
   "SCR_MN2": "",
   "SCR_ENG2": "",
   "DTVAL_CO": 184002
 },
 {
   "TBL_ID": "DT_NSO_1001_021V1",
   "Period": 2019,
   "CODE": 18213,
   "SCR_MN": "Бугат",
   "SCR_ENG": "Bugat",
   "CODE1": 1,
   "SCR_MN1": "Бүгд",
   "SCR_ENG1": "Total",
   "CODE2": "",
   "SCR_MN2": "",
   "SCR_ENG2": "",
   "DTVAL_CO": 181103
 },
 {
   "TBL_ID": "DT_NSO_1001_021V1",
   "Period": 2019,
   "CODE": 18216,
   "SCR_MN": "Дарив",
   "SCR_ENG": "Dariv",
   "CODE1": 1,
   "SCR_MN1": "Бүгд",
   "SCR_ENG1": "Total",
   "CODE2": "",
   "SCR_MN2": "",
   "SCR_ENG2": "",
   "DTVAL_CO": 119860
 },
 {
   "TBL_ID": "DT_NSO_1001_021V1",
   "Period": 2019,
   "CODE": 18219,
   "SCR_MN": "Дэлгэр",
   "SCR_ENG": "Delger",
   "CODE1": 1,
   "SCR_MN1": "Бүгд",
   "SCR_ENG1": "Total",
   "CODE2": "",
   "SCR_MN2": "",
   "SCR_ENG2": "",
   "DTVAL_CO": 305817
 },
 {
   "TBL_ID": "DT_NSO_1001_021V1",
   "Period": 2019,
   "CODE": 18222,
   "SCR_MN": "Жаргалан",
   "SCR_ENG": "Jargalan",
   "CODE1": 1,
   "SCR_MN1": "Бүгд",
   "SCR_ENG1": "Total",
   "CODE2": "",
   "SCR_MN2": "",
   "SCR_ENG2": "",
   "DTVAL_CO": 193835
 },
 {
   "TBL_ID": "DT_NSO_1001_021V1",
   "Period": 2019,
   "CODE": 18225,
   "SCR_MN": "Тайшир",
   "SCR_ENG": "Taishir",
   "CODE1": 1,
   "SCR_MN1": "Бүгд",
   "SCR_ENG1": "Total",
   "CODE2": "",
   "SCR_MN2": "",
   "SCR_ENG2": "",
   "DTVAL_CO": 132607
 },
 {
   "TBL_ID": "DT_NSO_1001_021V1",
   "Period": 2019,
   "CODE": 18228,
   "SCR_MN": "Тонхил",
   "SCR_ENG": "Tonkhil",
   "CODE1": 1,
   "SCR_MN1": "Бүгд",
   "SCR_ENG1": "Total",
   "CODE2": "",
   "SCR_MN2": "",
   "SCR_ENG2": "",
   "DTVAL_CO": 210048
 },
 {
   "TBL_ID": "DT_NSO_1001_021V1",
   "Period": 2019,
   "CODE": 18231,
   "SCR_MN": "Төгрөг",
   "SCR_ENG": "Tugrug",
   "CODE1": 1,
   "SCR_MN1": "Бүгд",
   "SCR_ENG1": "Total",
   "CODE2": "",
   "SCR_MN2": "",
   "SCR_ENG2": "",
   "DTVAL_CO": 121261
 },
 {
   "TBL_ID": "DT_NSO_1001_021V1",
   "Period": 2019,
   "CODE": 18234,
   "SCR_MN": "Халиун",
   "SCR_ENG": "Khaliun",
   "CODE1": 1,
   "SCR_MN1": "Бүгд",
   "SCR_ENG1": "Total",
   "CODE2": "",
   "SCR_MN2": "",
   "SCR_ENG2": "",
   "DTVAL_CO": 247231
 },
 {
   "TBL_ID": "DT_NSO_1001_021V1",
   "Period": 2019,
   "CODE": 18237,
   "SCR_MN": "Хөхморьт",
   "SCR_ENG": "Khukhmorit",
   "CODE1": 1,
   "SCR_MN1": "Бүгд",
   "SCR_ENG1": "Total",
   "CODE2": "",
   "SCR_MN2": "",
   "SCR_ENG2": "",
   "DTVAL_CO": 166910
 },
 {
   "TBL_ID": "DT_NSO_1001_021V1",
   "Period": 2019,
   "CODE": 18240,
   "SCR_MN": "Цогт",
   "SCR_ENG": "Tsogt",
   "CODE1": 1,
   "SCR_MN1": "Бүгд",
   "SCR_ENG1": "Total",
   "CODE2": "",
   "SCR_MN2": "",
   "SCR_ENG2": "",
   "DTVAL_CO": 300962
 },
 {
   "TBL_ID": "DT_NSO_1001_021V1",
   "Period": 2019,
   "CODE": 18243,
   "SCR_MN": "Цээл",
   "SCR_ENG": "Tseel",
   "CODE1": 1,
   "SCR_MN1": "Бүгд",
   "SCR_ENG1": "Total",
   "CODE2": "",
   "SCR_MN2": "",
   "SCR_ENG2": "",
   "DTVAL_CO": 217993
 },
 {
   "TBL_ID": "DT_NSO_1001_021V1",
   "Period": 2019,
   "CODE": 18246,
   "SCR_MN": "Чандмань",
   "SCR_ENG": "Chandmani",
   "CODE1": 1,
   "SCR_MN1": "Бүгд",
   "SCR_ENG1": "Total",
   "CODE2": "",
   "SCR_MN2": "",
   "SCR_ENG2": "",
   "DTVAL_CO": 229726
 },
 {
   "TBL_ID": "DT_NSO_1001_021V1",
   "Period": 2019,
   "CODE": 18249,
   "SCR_MN": "Шарга",
   "SCR_ENG": "Sharga",
   "CODE1": 1,
   "SCR_MN1": "Бүгд",
   "SCR_ENG1": "Total",
   "CODE2": "",
   "SCR_MN2": "",
   "SCR_ENG2": "",
   "DTVAL_CO": 165288
 },
 {
   "TBL_ID": "DT_NSO_1001_021V1",
   "Period": 2019,
   "CODE": 18252,
   "SCR_MN": "Эрдэнэ",
   "SCR_ENG": "Erdene",
   "CODE1": 1,
   "SCR_MN1": "Бүгд",
   "SCR_ENG1": "Total",
   "CODE2": "",
   "SCR_MN2": "",
   "SCR_ENG2": "",
   "DTVAL_CO": 244423
 },
 {
   "TBL_ID": "DT_NSO_1001_021V1",
   "Period": 2019,
   "CODE": 18301,
   "SCR_MN": "Өлгий",
   "SCR_ENG": "Ulgii",
   "CODE1": 1,
   "SCR_MN1": "Бүгд",
   "SCR_ENG1": "Total",
   "CODE2": "",
   "SCR_MN2": "",
   "SCR_ENG2": "",
   "DTVAL_CO": 27091
 },
 {
   "TBL_ID": "DT_NSO_1001_021V1",
   "Period": 2019,
   "CODE": 18304,
   "SCR_MN": "Алтай",
   "SCR_ENG": "Altai",
   "CODE1": 1,
   "SCR_MN1": "Бүгд",
   "SCR_ENG1": "Total",
   "CODE2": "",
   "SCR_MN2": "",
   "SCR_ENG2": "",
   "DTVAL_CO": 154714
 },
 {
   "TBL_ID": "DT_NSO_1001_021V1",
   "Period": 2019,
   "CODE": 18307,
   "SCR_MN": "Алтанцөгц",
   "SCR_ENG": "Altantsugts",
   "CODE1": 1,
   "SCR_MN1": "Бүгд",
   "SCR_ENG1": "Total",
   "CODE2": "",
   "SCR_MN2": "",
   "SCR_ENG2": "",
   "DTVAL_CO": 134258
 },
 {
   "TBL_ID": "DT_NSO_1001_021V1",
   "Period": 2019,
   "CODE": 18310,
   "SCR_MN": "Баяннуур",
   "SCR_ENG": "Bayannuur",
   "CODE1": 1,
   "SCR_MN1": "Бүгд",
   "SCR_ENG1": "Total",
   "CODE2": "",
   "SCR_MN2": "",
   "SCR_ENG2": "",
   "DTVAL_CO": 161224
 },
 {
   "TBL_ID": "DT_NSO_1001_021V1",
   "Period": 2019,
   "CODE": 18313,
   "SCR_MN": "Бугат",
   "SCR_ENG": "Bugat",
   "CODE1": 1,
   "SCR_MN1": "Бүгд",
   "SCR_ENG1": "Total",
   "CODE2": "",
   "SCR_MN2": "",
   "SCR_ENG2": "",
   "DTVAL_CO": 119690
 },
 {
   "TBL_ID": "DT_NSO_1001_021V1",
   "Period": 2019,
   "CODE": 18316,
   "SCR_MN": "Булган",
   "SCR_ENG": "Bulgan",
   "CODE1": 1,
   "SCR_MN1": "Бүгд",
   "SCR_ENG1": "Total",
   "CODE2": "",
   "SCR_MN2": "",
   "SCR_ENG2": "",
   "DTVAL_CO": 130311
 },
 {
   "TBL_ID": "DT_NSO_1001_021V1",
   "Period": 2019,
   "CODE": 18319,
   "SCR_MN": "Буянт",
   "SCR_ENG": "Buyant",
   "CODE1": 1,
   "SCR_MN1": "Бүгд",
   "SCR_ENG1": "Total",
   "CODE2": "",
   "SCR_MN2": "",
   "SCR_ENG2": "",
   "DTVAL_CO": 131898
 },
 {
   "TBL_ID": "DT_NSO_1001_021V1",
   "Period": 2019,
   "CODE": 18322,
   "SCR_MN": "Дэлүүн",
   "SCR_ENG": "Deluun",
   "CODE1": 1,
   "SCR_MN1": "Бүгд",
   "SCR_ENG1": "Total",
   "CODE2": "",
   "SCR_MN2": "",
   "SCR_ENG2": "",
   "DTVAL_CO": 228875
 },
 {
   "TBL_ID": "DT_NSO_1001_021V1",
   "Period": 2019,
   "CODE": 18325,
   "SCR_MN": "Ногооннуур",
   "SCR_ENG": "Nogoonnuur",
   "CODE1": 1,
   "SCR_MN1": "Бүгд",
   "SCR_ENG1": "Total",
   "CODE2": "",
   "SCR_MN2": "",
   "SCR_ENG2": "",
   "DTVAL_CO": 241843
 },
 {
   "TBL_ID": "DT_NSO_1001_021V1",
   "Period": 2019,
   "CODE": 18328,
   "SCR_MN": "Сагсай",
   "SCR_ENG": "Sagsai",
   "CODE1": 1,
   "SCR_MN1": "Бүгд",
   "SCR_ENG1": "Total",
   "CODE2": "",
   "SCR_MN2": "",
   "SCR_ENG2": "",
   "DTVAL_CO": 158957
 },
 {
   "TBL_ID": "DT_NSO_1001_021V1",
   "Period": 2019,
   "CODE": 18331,
   "SCR_MN": "Толбо",
   "SCR_ENG": "Tolbo",
   "CODE1": 1,
   "SCR_MN1": "Бүгд",
   "SCR_ENG1": "Total",
   "CODE2": "",
   "SCR_MN2": "",
   "SCR_ENG2": "",
   "DTVAL_CO": 170269
 },
 {
   "TBL_ID": "DT_NSO_1001_021V1",
   "Period": 2019,
   "CODE": 18334,
   "SCR_MN": "Улаанхус",
   "SCR_ENG": "Ulaankhus",
   "CODE1": 1,
   "SCR_MN1": "Бүгд",
   "SCR_ENG1": "Total",
   "CODE2": "",
   "SCR_MN2": "",
   "SCR_ENG2": "",
   "DTVAL_CO": 221032
 },
 {
   "TBL_ID": "DT_NSO_1001_021V1",
   "Period": 2019,
   "CODE": 18337,
   "SCR_MN": "Цэнгэл",
   "SCR_ENG": "Tsengel",
   "CODE1": 1,
   "SCR_MN1": "Бүгд",
   "SCR_ENG1": "Total",
   "CODE2": "",
   "SCR_MN2": "",
   "SCR_ENG2": "",
   "DTVAL_CO": 312602
 },
 {
   "TBL_ID": "DT_NSO_1001_021V1",
   "Period": 2019,
   "CODE": 18401,
   "SCR_MN": "Жаргалант",
   "SCR_ENG": "Jargalant",
   "CODE1": 1,
   "SCR_MN1": "Бүгд",
   "SCR_ENG1": "Total",
   "CODE2": "",
   "SCR_MN2": "",
   "SCR_ENG2": "",
   "DTVAL_CO": 96187
 },
 {
   "TBL_ID": "DT_NSO_1001_021V1",
   "Period": 2019,
   "CODE": 18404,
   "SCR_MN": "Алтай",
   "SCR_ENG": "Altai",
   "CODE1": 1,
   "SCR_MN1": "Бүгд",
   "SCR_ENG1": "Total",
   "CODE2": "",
   "SCR_MN2": "",
   "SCR_ENG2": "",
   "DTVAL_CO": 215003
 },
 {
   "TBL_ID": "DT_NSO_1001_021V1",
   "Period": 2019,
   "CODE": 18410,
   "SCR_MN": "Буянт",
   "SCR_ENG": "Buyant",
   "CODE1": 1,
   "SCR_MN1": "Бүгд",
   "SCR_ENG1": "Total",
   "CODE2": "",
   "SCR_MN2": "",
   "SCR_ENG2": "",
   "DTVAL_CO": 184627
 },
 {
   "TBL_ID": "DT_NSO_1001_021V1",
   "Period": 2019,
   "CODE": 18413,
   "SCR_MN": "Дарви",
   "SCR_ENG": "Darvi",
   "CODE1": 1,
   "SCR_MN1": "Бүгд",
   "SCR_ENG1": "Total",
   "CODE2": "",
   "SCR_MN2": "",
   "SCR_ENG2": "",
   "DTVAL_CO": 214437
 },
 {
   "TBL_ID": "DT_NSO_1001_021V1",
   "Period": 2019,
   "CODE": 18416,
   "SCR_MN": "Дөргөн",
   "SCR_ENG": "Durgun",
   "CODE1": 1,
   "SCR_MN1": "Бүгд",
   "SCR_ENG1": "Total",
   "CODE2": "",
   "SCR_MN2": "",
   "SCR_ENG2": "",
   "DTVAL_CO": 136197
 },
 {
   "TBL_ID": "DT_NSO_1001_021V1",
   "Period": 2019,
   "CODE": 18419,
   "SCR_MN": "Дуут",
   "SCR_ENG": "Duut",
   "CODE1": 1,
   "SCR_MN1": "Бүгд",
   "SCR_ENG1": "Total",
   "CODE2": "",
   "SCR_MN2": "",
   "SCR_ENG2": "",
   "DTVAL_CO": 127607
 },
 {
   "TBL_ID": "DT_NSO_1001_021V1",
   "Period": 2019,
   "CODE": 18422,
   "SCR_MN": "Зэрэг",
   "SCR_ENG": "Zereg",
   "CODE1": 1,
   "SCR_MN1": "Бүгд",
   "SCR_ENG1": "Total",
   "CODE2": "",
   "SCR_MN2": "",
   "SCR_ENG2": "",
   "DTVAL_CO": 151643
 },
 {
   "TBL_ID": "DT_NSO_1001_021V1",
   "Period": 2019,
   "CODE": 18425,
   "SCR_MN": "Манхан",
   "SCR_ENG": "Mankhan",
   "CODE1": 1,
   "SCR_MN1": "Бүгд",
   "SCR_ENG1": "Total",
   "CODE2": "",
   "SCR_MN2": "",
   "SCR_ENG2": "",
   "DTVAL_CO": 226199
 },
 {
   "TBL_ID": "DT_NSO_1001_021V1",
   "Period": 2019,
   "CODE": 18428,
   "SCR_MN": "Мөнххайрхан",
   "SCR_ENG": "Munkhkhairkhan",
   "CODE1": 1,
   "SCR_MN1": "Бүгд",
   "SCR_ENG1": "Total",
   "CODE2": "",
   "SCR_MN2": "",
   "SCR_ENG2": "",
   "DTVAL_CO": 111056
 },
 {
   "TBL_ID": "DT_NSO_1001_021V1",
   "Period": 2019,
   "CODE": 18431,
   "SCR_MN": "Мөст",
   "SCR_ENG": "Must",
   "CODE1": 1,
   "SCR_MN1": "Бүгд",
   "SCR_ENG1": "Total",
   "CODE2": "",
   "SCR_MN2": "",
   "SCR_ENG2": "",
   "DTVAL_CO": 192276
 },
 {
   "TBL_ID": "DT_NSO_1001_021V1",
   "Period": 2019,
   "CODE": 18434,
   "SCR_MN": "Мянгад",
   "SCR_ENG": "Myangad",
   "CODE1": 1,
   "SCR_MN1": "Бүгд",
   "SCR_ENG1": "Total",
   "CODE2": "",
   "SCR_MN2": "",
   "SCR_ENG2": "",
   "DTVAL_CO": 227695
 },
 {
   "TBL_ID": "DT_NSO_1001_021V1",
   "Period": 2019,
   "CODE": 18437,
   "SCR_MN": "Үенч",
   "SCR_ENG": "Uyench",
   "CODE1": 1,
   "SCR_MN1": "Бүгд",
   "SCR_ENG1": "Total",
   "CODE2": "",
   "SCR_MN2": "",
   "SCR_ENG2": "",
   "DTVAL_CO": 158645
 },
 {
   "TBL_ID": "DT_NSO_1001_021V1",
   "Period": 2019,
   "CODE": 18440,
   "SCR_MN": "Ховд",
   "SCR_ENG": "Khovd",
   "CODE1": 1,
   "SCR_MN1": "Бүгд",
   "SCR_ENG1": "Total",
   "CODE2": "",
   "SCR_MN2": "",
   "SCR_ENG2": "",
   "DTVAL_CO": 175738
 },
 {
   "TBL_ID": "DT_NSO_1001_021V1",
   "Period": 2019,
   "CODE": 18443,
   "SCR_MN": "Цэцэг",
   "SCR_ENG": "Tsetseg",
   "CODE1": 1,
   "SCR_MN1": "Бүгд",
   "SCR_ENG1": "Total",
   "CODE2": "",
   "SCR_MN2": "",
   "SCR_ENG2": "",
   "DTVAL_CO": 173272
 },
 {
   "TBL_ID": "DT_NSO_1001_021V1",
   "Period": 2019,
   "CODE": 18446,
   "SCR_MN": "Чандмань",
   "SCR_ENG": "Chandmani",
   "CODE1": 1,
   "SCR_MN1": "Бүгд",
   "SCR_ENG1": "Total",
   "CODE2": "",
   "SCR_MN2": "",
   "SCR_ENG2": "",
   "DTVAL_CO": 222238
 },
 {
   "TBL_ID": "DT_NSO_1001_021V1",
   "Period": 2019,
   "CODE": 18449,
   "SCR_MN": "Эрдэнэбүрэн",
   "SCR_ENG": "Erdeneburen",
   "CODE1": 1,
   "SCR_MN1": "Бүгд",
   "SCR_ENG1": "Total",
   "CODE2": "",
   "SCR_MN2": "",
   "SCR_ENG2": "",
   "DTVAL_CO": 156857
 },
 {
   "TBL_ID": "DT_NSO_1001_021V1",
   "Period": 2019,
   "CODE": 18501,
   "SCR_MN": "Улаангом",
   "SCR_ENG": "Ulaangom",
   "CODE1": 1,
   "SCR_MN1": "Бүгд",
   "SCR_ENG1": "Total",
   "CODE2": "",
   "SCR_MN2": "",
   "SCR_ENG2": "",
   "DTVAL_CO": 216142
 },
 {
   "TBL_ID": "DT_NSO_1001_021V1",
   "Period": 2019,
   "CODE": 18504,
   "SCR_MN": "Баруунтуруун",
   "SCR_ENG": "Baruunturuun",
   "CODE1": 1,
   "SCR_MN1": "Бүгд",
   "SCR_ENG1": "Total",
   "CODE2": "",
   "SCR_MN2": "",
   "SCR_ENG2": "",
   "DTVAL_CO": 78072
 },
 {
   "TBL_ID": "DT_NSO_1001_021V1",
   "Period": 2019,
   "CODE": 18507,
   "SCR_MN": "Бөхмөрөн",
   "SCR_ENG": "Bukhmurun",
   "CODE1": 1,
   "SCR_MN1": "Бүгд",
   "SCR_ENG1": "Total",
   "CODE2": "",
   "SCR_MN2": "",
   "SCR_ENG2": "",
   "DTVAL_CO": 140469
 },
 {
   "TBL_ID": "DT_NSO_1001_021V1",
   "Period": 2019,
   "CODE": 18510,
   "SCR_MN": "Давст",
   "SCR_ENG": "Davst",
   "CODE1": 1,
   "SCR_MN1": "Бүгд",
   "SCR_ENG1": "Total",
   "CODE2": "",
   "SCR_MN2": "",
   "SCR_ENG2": "",
   "DTVAL_CO": 98507
 },
 {
   "TBL_ID": "DT_NSO_1001_021V1",
   "Period": 2019,
   "CODE": 18513,
   "SCR_MN": "Завхан",
   "SCR_ENG": "Zavkhan",
   "CODE1": 1,
   "SCR_MN1": "Бүгд",
   "SCR_ENG1": "Total",
   "CODE2": "",
   "SCR_MN2": "",
   "SCR_ENG2": "",
   "DTVAL_CO": 130855
 },
 {
   "TBL_ID": "DT_NSO_1001_021V1",
   "Period": 2019,
   "CODE": 18516,
   "SCR_MN": "Зүүнговь",
   "SCR_ENG": "Zuungovi",
   "CODE1": 1,
   "SCR_MN1": "Бүгд",
   "SCR_ENG1": "Total",
   "CODE2": "",
   "SCR_MN2": "",
   "SCR_ENG2": "",
   "DTVAL_CO": 142496
 },
 {
   "TBL_ID": "DT_NSO_1001_021V1",
   "Period": 2019,
   "CODE": 18519,
   "SCR_MN": "Зүүнхангай",
   "SCR_ENG": "Zuunkhangai",
   "CODE1": 1,
   "SCR_MN1": "Бүгд",
   "SCR_ENG1": "Total",
   "CODE2": "",
   "SCR_MN2": "",
   "SCR_ENG2": "",
   "DTVAL_CO": 178428
 },
 {
   "TBL_ID": "DT_NSO_1001_021V1",
   "Period": 2019,
   "CODE": 18522,
   "SCR_MN": "Малчин",
   "SCR_ENG": "Malchin",
   "CODE1": 1,
   "SCR_MN1": "Бүгд",
   "SCR_ENG1": "Total",
   "CODE2": "",
   "SCR_MN2": "",
   "SCR_ENG2": "",
   "DTVAL_CO": 174287
 },
 {
   "TBL_ID": "DT_NSO_1001_021V1",
   "Period": 2019,
   "CODE": 18525,
   "SCR_MN": "Наранбулаг",
   "SCR_ENG": "Naranbulag",
   "CODE1": 1,
   "SCR_MN1": "Бүгд",
   "SCR_ENG1": "Total",
   "CODE2": "",
   "SCR_MN2": "",
   "SCR_ENG2": "",
   "DTVAL_CO": 233055
 },
 {
   "TBL_ID": "DT_NSO_1001_021V1",
   "Period": 2019,
   "CODE": 18528,
   "SCR_MN": "Өлгий",
   "SCR_ENG": "Ulgii",
   "CODE1": 1,
   "SCR_MN1": "Бүгд",
   "SCR_ENG1": "Total",
   "CODE2": "",
   "SCR_MN2": "",
   "SCR_ENG2": "",
   "DTVAL_CO": 115024
 },
 {
   "TBL_ID": "DT_NSO_1001_021V1",
   "Period": 2019,
   "CODE": 18531,
   "SCR_MN": "Өмнөговь",
   "SCR_ENG": "Umnugovi",
   "CODE1": 1,
   "SCR_MN1": "Бүгд",
   "SCR_ENG1": "Total",
   "CODE2": "",
   "SCR_MN2": "",
   "SCR_ENG2": "",
   "DTVAL_CO": 211186
 },
 {
   "TBL_ID": "DT_NSO_1001_021V1",
   "Period": 2019,
   "CODE": 18534,
   "SCR_MN": "Өндөрхангай",
   "SCR_ENG": "Undurkhangai",
   "CODE1": 1,
   "SCR_MN1": "Бүгд",
   "SCR_ENG1": "Total",
   "CODE2": "",
   "SCR_MN2": "",
   "SCR_ENG2": "",
   "DTVAL_CO": 236586
 },
 {
   "TBL_ID": "DT_NSO_1001_021V1",
   "Period": 2019,
   "CODE": 18537,
   "SCR_MN": "Сагил",
   "SCR_ENG": "Sagil",
   "CODE1": 1,
   "SCR_MN1": "Бүгд",
   "SCR_ENG1": "Total",
   "CODE2": "",
   "SCR_MN2": "",
   "SCR_ENG2": "",
   "DTVAL_CO": 187033
 },
 {
   "TBL_ID": "DT_NSO_1001_021V1",
   "Period": 2019,
   "CODE": 18540,
   "SCR_MN": "Тариалан",
   "SCR_ENG": "Tarialan",
   "CODE1": 1,
   "SCR_MN1": "Бүгд",
   "SCR_ENG1": "Total",
   "CODE2": "",
   "SCR_MN2": "",
   "SCR_ENG2": "",
   "DTVAL_CO": 150192
 },
 {
   "TBL_ID": "DT_NSO_1001_021V1",
   "Period": 2019,
   "CODE": 18543,
   "SCR_MN": "Түргэн",
   "SCR_ENG": "Turgen",
   "CODE1": 1,
   "SCR_MN1": "Бүгд",
   "SCR_ENG1": "Total",
   "CODE2": "",
   "SCR_MN2": "",
   "SCR_ENG2": "",
   "DTVAL_CO": 144623
 },
 {
   "TBL_ID": "DT_NSO_1001_021V1",
   "Period": 2019,
   "CODE": 18546,
   "SCR_MN": "Тэс",
   "SCR_ENG": "Tes",
   "CODE1": 1,
   "SCR_MN1": "Бүгд",
   "SCR_ENG1": "Total",
   "CODE2": "",
   "SCR_MN2": "",
   "SCR_ENG2": "",
   "DTVAL_CO": 287902
 },
 {
   "TBL_ID": "DT_NSO_1001_021V1",
   "Period": 2019,
   "CODE": 18549,
   "SCR_MN": "Ховд",
   "SCR_ENG": "Khovd",
   "CODE1": 1,
   "SCR_MN1": "Бүгд",
   "SCR_ENG1": "Total",
   "CODE2": "",
   "SCR_MN2": "",
   "SCR_ENG2": "",
   "DTVAL_CO": 162956
 },
 {
   "TBL_ID": "DT_NSO_1001_021V1",
   "Period": 2019,
   "CODE": 18552,
   "SCR_MN": "Хяргас",
   "SCR_ENG": "Khyargas",
   "CODE1": 1,
   "SCR_MN1": "Бүгд",
   "SCR_ENG1": "Total",
   "CODE2": "",
   "SCR_MN2": "",
   "SCR_ENG2": "",
   "DTVAL_CO": 208440
 },
 {
   "TBL_ID": "DT_NSO_1001_021V1",
   "Period": 2019,
   "CODE": 18555,
   "SCR_MN": "Цагаанхайрхан",
   "SCR_ENG": "Tsagaankhairkhan",
   "CODE1": 1,
   "SCR_MN1": "Бүгд",
   "SCR_ENG1": "Total",
   "CODE2": "",
   "SCR_MN2": "",
   "SCR_ENG2": "",
   "DTVAL_CO": 183347
 },
 {
   "TBL_ID": "DT_NSO_1001_021V1",
   "Period": 2019,
   "CODE": 26101,
   "SCR_MN": "Баян-Өндөр",
   "SCR_ENG": "Bayan-Undur",
   "CODE1": 1,
   "SCR_MN1": "Бүгд",
   "SCR_ENG1": "Total",
   "CODE2": "",
   "SCR_MN2": "",
   "SCR_ENG2": "",
   "DTVAL_CO": 59291
 },
 {
   "TBL_ID": "DT_NSO_1001_021V1",
   "Period": 2019,
   "CODE": 26104,
   "SCR_MN": "Жаргалант",
   "SCR_ENG": "Jargalant",
   "CODE1": 1,
   "SCR_MN1": "Бүгд",
   "SCR_ENG1": "Total",
   "CODE2": "",
   "SCR_MN2": "",
   "SCR_ENG2": "",
   "DTVAL_CO": 67657
 },
 {
   "TBL_ID": "DT_NSO_1001_021V1",
   "Period": 2019,
   "CODE": 26201,
   "SCR_MN": "Арвайхээр",
   "SCR_ENG": "Arvaikheer",
   "CODE1": 1,
   "SCR_MN1": "Бүгд",
   "SCR_ENG1": "Total",
   "CODE2": "",
   "SCR_MN2": "",
   "SCR_ENG2": "",
   "DTVAL_CO": 258795
 },
 {
   "TBL_ID": "DT_NSO_1001_021V1",
   "Period": 2019,
   "CODE": 26204,
   "SCR_MN": "Баруунбаян-Улаан",
   "SCR_ENG": "Baruunbayan-Ulaan",
   "CODE1": 1,
   "SCR_MN1": "Бүгд",
   "SCR_ENG1": "Total",
   "CODE2": "",
   "SCR_MN2": "",
   "SCR_ENG2": "",
   "DTVAL_CO": 198547
 },
 {
   "TBL_ID": "DT_NSO_1001_021V1",
   "Period": 2019,
   "CODE": 26207,
   "SCR_MN": "Бат-Өлзий",
   "SCR_ENG": "Bat-Ulzii",
   "CODE1": 1,
   "SCR_MN1": "Бүгд",
   "SCR_ENG1": "Total",
   "CODE2": "",
   "SCR_MN2": "",
   "SCR_ENG2": "",
   "DTVAL_CO": 335569
 },
 {
   "TBL_ID": "DT_NSO_1001_021V1",
   "Period": 2019,
   "CODE": 26210,
   "SCR_MN": "Баянгол",
   "SCR_ENG": "Bayangol",
   "CODE1": 1,
   "SCR_MN1": "Бүгд",
   "SCR_ENG1": "Total",
   "CODE2": "",
   "SCR_MN2": "",
   "SCR_ENG2": "",
   "DTVAL_CO": 387856
 },
 {
   "TBL_ID": "DT_NSO_1001_021V1",
   "Period": 2019,
   "CODE": 26213,
   "SCR_MN": "Баян-Өндөр",
   "SCR_ENG": "Bayan-Undur",
   "CODE1": 1,
   "SCR_MN1": "Бүгд",
   "SCR_ENG1": "Total",
   "CODE2": "",
   "SCR_MN2": "",
   "SCR_ENG2": "",
   "DTVAL_CO": 353125
 },
 {
   "TBL_ID": "DT_NSO_1001_021V1",
   "Period": 2019,
   "CODE": 26216,
   "SCR_MN": "Богд",
   "SCR_ENG": "Bogd",
   "CODE1": 1,
   "SCR_MN1": "Бүгд",
   "SCR_ENG1": "Total",
   "CODE2": "",
   "SCR_MN2": "",
   "SCR_ENG2": "",
   "DTVAL_CO": 514547
 },
 {
   "TBL_ID": "DT_NSO_1001_021V1",
   "Period": 2019,
   "CODE": 26219,
   "SCR_MN": "Бүрд",
   "SCR_ENG": "Burd",
   "CODE1": 1,
   "SCR_MN1": "Бүгд",
   "SCR_ENG1": "Total",
   "CODE2": "",
   "SCR_MN2": "",
   "SCR_ENG2": "",
   "DTVAL_CO": 324656
 },
 {
   "TBL_ID": "DT_NSO_1001_021V1",
   "Period": 2019,
   "CODE": 26222,
   "SCR_MN": "Гучин-Ус",
   "SCR_ENG": "Guchin-Us",
   "CODE1": 1,
   "SCR_MN1": "Бүгд",
   "SCR_ENG1": "Total",
   "CODE2": "",
   "SCR_MN2": "",
   "SCR_ENG2": "",
   "DTVAL_CO": 235479
 },
 {
   "TBL_ID": "DT_NSO_1001_021V1",
   "Period": 2019,
   "CODE": 26225,
   "SCR_MN": "Есөн зүйл",
   "SCR_ENG": "Yesun zuil",
   "CODE1": 1,
   "SCR_MN1": "Бүгд",
   "SCR_ENG1": "Total",
   "CODE2": "",
   "SCR_MN2": "",
   "SCR_ENG2": "",
   "DTVAL_CO": 198810
 },
 {
   "TBL_ID": "DT_NSO_1001_021V1",
   "Period": 2019,
   "CODE": 26228,
   "SCR_MN": "Зүүнбаян-Улаан",
   "SCR_ENG": "Zuunbayan-Ulaan",
   "CODE1": 1,
   "SCR_MN1": "Бүгд",
   "SCR_ENG1": "Total",
   "CODE2": "",
   "SCR_MN2": "",
   "SCR_ENG2": "",
   "DTVAL_CO": 272872
 },
 {
   "TBL_ID": "DT_NSO_1001_021V1",
   "Period": 2019,
   "CODE": 26231,
   "SCR_MN": "Нарийнтээл",
   "SCR_ENG": "Nariinteel",
   "CODE1": 1,
   "SCR_MN1": "Бүгд",
   "SCR_ENG1": "Total",
   "CODE2": "",
   "SCR_MN2": "",
   "SCR_ENG2": "",
   "DTVAL_CO": 222810
 },
 {
   "TBL_ID": "DT_NSO_1001_021V1",
   "Period": 2019,
   "CODE": 26234,
   "SCR_MN": "Өлзийт",
   "SCR_ENG": "Ulziit",
   "CODE1": 1,
   "SCR_MN1": "Бүгд",
   "SCR_ENG1": "Total",
   "CODE2": "",
   "SCR_MN2": "",
   "SCR_ENG2": "",
   "DTVAL_CO": 213993
 },
 {
   "TBL_ID": "DT_NSO_1001_021V1",
   "Period": 2019,
   "CODE": 26237,
   "SCR_MN": "Сант",
   "SCR_ENG": "Sant",
   "CODE1": 1,
   "SCR_MN1": "Бүгд",
   "SCR_ENG1": "Total",
   "CODE2": "",
   "SCR_MN2": "",
   "SCR_ENG2": "",
   "DTVAL_CO": 277178
 },
 {
   "TBL_ID": "DT_NSO_1001_021V1",
   "Period": 2019,
   "CODE": 26240,
   "SCR_MN": "Тарагт",
   "SCR_ENG": "Taragt",
   "CODE1": 1,
   "SCR_MN1": "Бүгд",
   "SCR_ENG1": "Total",
   "CODE2": "",
   "SCR_MN2": "",
   "SCR_ENG2": "",
   "DTVAL_CO": 251631
 },
 {
   "TBL_ID": "DT_NSO_1001_021V1",
   "Period": 2019,
   "CODE": 26243,
   "SCR_MN": "Төгрөг",
   "SCR_ENG": "Tugrug",
   "CODE1": 1,
   "SCR_MN1": "Бүгд",
   "SCR_ENG1": "Total",
   "CODE2": "",
   "SCR_MN2": "",
   "SCR_ENG2": "",
   "DTVAL_CO": 246220
 },
 {
   "TBL_ID": "DT_NSO_1001_021V1",
   "Period": 2019,
   "CODE": 26246,
   "SCR_MN": "Уянга",
   "SCR_ENG": "Uyanga",
   "CODE1": 1,
   "SCR_MN1": "Бүгд",
   "SCR_ENG1": "Total",
   "CODE2": "",
   "SCR_MN2": "",
   "SCR_ENG2": "",
   "DTVAL_CO": 378451
 },
 {
   "TBL_ID": "DT_NSO_1001_021V1",
   "Period": 2019,
   "CODE": 26249,
   "SCR_MN": "Хайрхандулаан",
   "SCR_ENG": "Khairkhandulaan",
   "CODE1": 1,
   "SCR_MN1": "Бүгд",
   "SCR_ENG1": "Total",
   "CODE2": "",
   "SCR_MN2": "",
   "SCR_ENG2": "",
   "DTVAL_CO": 312024
 },
 {
   "TBL_ID": "DT_NSO_1001_021V1",
   "Period": 2019,
   "CODE": 26252,
   "SCR_MN": "Хархорин",
   "SCR_ENG": "Kharkhorin",
   "CODE1": 1,
   "SCR_MN1": "Бүгд",
   "SCR_ENG1": "Total",
   "CODE2": "",
   "SCR_MN2": "",
   "SCR_ENG2": "",
   "DTVAL_CO": 352068
 },
 {
   "TBL_ID": "DT_NSO_1001_021V1",
   "Period": 2019,
   "CODE": 26255,
   "SCR_MN": "Хужирт",
   "SCR_ENG": "Khujirt",
   "CODE1": 1,
   "SCR_MN1": "Бүгд",
   "SCR_ENG1": "Total",
   "CODE2": "",
   "SCR_MN2": "",
   "SCR_ENG2": "",
   "DTVAL_CO": 290832
 },
 {
   "TBL_ID": "DT_NSO_1001_021V1",
   "Period": 2019,
   "CODE": 26301,
   "SCR_MN": "Булган",
   "SCR_ENG": "Bulgan",
   "CODE1": 1,
   "SCR_MN1": "Бүгд",
   "SCR_ENG1": "Total",
   "CODE2": "",
   "SCR_MN2": "",
   "SCR_ENG2": "",
   "DTVAL_CO": 69582
 },
 {
   "TBL_ID": "DT_NSO_1001_021V1",
   "Period": 2019,
   "CODE": 26304,
   "SCR_MN": "Баян-Агт",
   "SCR_ENG": "Bayan-Agt",
   "CODE1": 1,
   "SCR_MN1": "Бүгд",
   "SCR_ENG1": "Total",
   "CODE2": "",
   "SCR_MN2": "",
   "SCR_ENG2": "",
   "DTVAL_CO": 321694
 },
 {
   "TBL_ID": "DT_NSO_1001_021V1",
   "Period": 2019,
   "CODE": 26307,
   "SCR_MN": "Баяннуур",
   "SCR_ENG": "Bayannuur",
   "CODE1": 1,
   "SCR_MN1": "Бүгд",
   "SCR_ENG1": "Total",
   "CODE2": "",
   "SCR_MN2": "",
   "SCR_ENG2": "",
   "DTVAL_CO": 137019
 },
 {
   "TBL_ID": "DT_NSO_1001_021V1",
   "Period": 2019,
   "CODE": 26310,
   "SCR_MN": "Бугат",
   "SCR_ENG": "Bugat",
   "CODE1": 1,
   "SCR_MN1": "Бүгд",
   "SCR_ENG1": "Total",
   "CODE2": "",
   "SCR_MN2": "",
   "SCR_ENG2": "",
   "DTVAL_CO": 111463
 },
 {
   "TBL_ID": "DT_NSO_1001_021V1",
   "Period": 2019,
   "CODE": 26313,
   "SCR_MN": "Бүрэгхангай",
   "SCR_ENG": "Buregkhangai",
   "CODE1": 1,
   "SCR_MN1": "Бүгд",
   "SCR_ENG1": "Total",
   "CODE2": "",
   "SCR_MN2": "",
   "SCR_ENG2": "",
   "DTVAL_CO": 321449
 },
 {
   "TBL_ID": "DT_NSO_1001_021V1",
   "Period": 2019,
   "CODE": 26316,
   "SCR_MN": "Гурванбулаг",
   "SCR_ENG": "Gurvanbulag",
   "CODE1": 1,
   "SCR_MN1": "Бүгд",
   "SCR_ENG1": "Total",
   "CODE2": "",
   "SCR_MN2": "",
   "SCR_ENG2": "",
   "DTVAL_CO": 326638
 },
 {
   "TBL_ID": "DT_NSO_1001_021V1",
   "Period": 2019,
   "CODE": 26319,
   "SCR_MN": "Дашинчилэн",
   "SCR_ENG": "Dashinchilen",
   "CODE1": 1,
   "SCR_MN1": "Бүгд",
   "SCR_ENG1": "Total",
   "CODE2": "",
   "SCR_MN2": "",
   "SCR_ENG2": "",
   "DTVAL_CO": 261860
 },
 {
   "TBL_ID": "DT_NSO_1001_021V1",
   "Period": 2019,
   "CODE": 26322,
   "SCR_MN": "Могод",
   "SCR_ENG": "Mogod",
   "CODE1": 1,
   "SCR_MN1": "Бүгд",
   "SCR_ENG1": "Total",
   "CODE2": "",
   "SCR_MN2": "",
   "SCR_ENG2": "",
   "DTVAL_CO": 329596
 },
 {
   "TBL_ID": "DT_NSO_1001_021V1",
   "Period": 2019,
   "CODE": 26325,
   "SCR_MN": "Орхон",
   "SCR_ENG": "Orkhon",
   "CODE1": 1,
   "SCR_MN1": "Бүгд",
   "SCR_ENG1": "Total",
   "CODE2": "",
   "SCR_MN2": "",
   "SCR_ENG2": "",
   "DTVAL_CO": 327477
 },
 {
   "TBL_ID": "DT_NSO_1001_021V1",
   "Period": 2019,
   "CODE": 26328,
   "SCR_MN": "Рашаант",
   "SCR_ENG": "Rashaant",
   "CODE1": 1,
   "SCR_MN1": "Бүгд",
   "SCR_ENG1": "Total",
   "CODE2": "",
   "SCR_MN2": "",
   "SCR_ENG2": "",
   "DTVAL_CO": 198039
 },
 {
   "TBL_ID": "DT_NSO_1001_021V1",
   "Period": 2019,
   "CODE": 26331,
   "SCR_MN": "Сайхан",
   "SCR_ENG": "Saikhan",
   "CODE1": 1,
   "SCR_MN1": "Бүгд",
   "SCR_ENG1": "Total",
   "CODE2": "",
   "SCR_MN2": "",
   "SCR_ENG2": "",
   "DTVAL_CO": 373702
 },
 {
   "TBL_ID": "DT_NSO_1001_021V1",
   "Period": 2019,
   "CODE": 26334,
   "SCR_MN": "Сэлэнгэ",
   "SCR_ENG": "Selenge",
   "CODE1": 1,
   "SCR_MN1": "Бүгд",
   "SCR_ENG1": "Total",
   "CODE2": "",
   "SCR_MN2": "",
   "SCR_ENG2": "",
   "DTVAL_CO": 100354
 },
 {
   "TBL_ID": "DT_NSO_1001_021V1",
   "Period": 2019,
   "CODE": 26337,
   "SCR_MN": "Тэшиг",
   "SCR_ENG": "Teshig",
   "CODE1": 1,
   "SCR_MN1": "Бүгд",
   "SCR_ENG1": "Total",
   "CODE2": "",
   "SCR_MN2": "",
   "SCR_ENG2": "",
   "DTVAL_CO": 90123
 },
 {
   "TBL_ID": "DT_NSO_1001_021V1",
   "Period": 2019,
   "CODE": 26340,
   "SCR_MN": "Хангал",
   "SCR_ENG": "Khangal",
   "CODE1": 1,
   "SCR_MN1": "Бүгд",
   "SCR_ENG1": "Total",
   "CODE2": "",
   "SCR_MN2": "",
   "SCR_ENG2": "",
   "DTVAL_CO": 93547
 },
 {
   "TBL_ID": "DT_NSO_1001_021V1",
   "Period": 2019,
   "CODE": 26343,
   "SCR_MN": "Хишиг-Өндөр",
   "SCR_ENG": "Khishig-Undur",
   "CODE1": 1,
   "SCR_MN1": "Бүгд",
   "SCR_ENG1": "Total",
   "CODE2": "",
   "SCR_MN2": "",
   "SCR_ENG2": "",
   "DTVAL_CO": 245457
 },
 {
   "TBL_ID": "DT_NSO_1001_021V1",
   "Period": 2019,
   "CODE": 26346,
   "SCR_MN": "Хутаг-Өндөр",
   "SCR_ENG": "Khutag-Undur",
   "CODE1": 1,
   "SCR_MN1": "Бүгд",
   "SCR_ENG1": "Total",
   "CODE2": "",
   "SCR_MN2": "",
   "SCR_ENG2": "",
   "DTVAL_CO": 333704
 },
 {
   "TBL_ID": "DT_NSO_1001_021V1",
   "Period": 2019,
   "CODE": 26401,
   "SCR_MN": "Баянхонгор",
   "SCR_ENG": "Bayankhongor",
   "CODE1": 1,
   "SCR_MN1": "Бүгд",
   "SCR_ENG1": "Total",
   "CODE2": "",
   "SCR_MN2": "",
   "SCR_ENG2": "",
   "DTVAL_CO": 175891
 },
 {
   "TBL_ID": "DT_NSO_1001_021V1",
   "Period": 2019,
   "CODE": 26404,
   "SCR_MN": "Баацагаан",
   "SCR_ENG": "Baatsagaan",
   "CODE1": 1,
   "SCR_MN1": "Бүгд",
   "SCR_ENG1": "Total",
   "CODE2": "",
   "SCR_MN2": "",
   "SCR_ENG2": "",
   "DTVAL_CO": 368315
 },
 {
   "TBL_ID": "DT_NSO_1001_021V1",
   "Period": 2019,
   "CODE": 26407,
   "SCR_MN": "Баянбулаг",
   "SCR_ENG": "Bayanbulag",
   "CODE1": 1,
   "SCR_MN1": "Бүгд",
   "SCR_ENG1": "Total",
   "CODE2": "",
   "SCR_MN2": "",
   "SCR_ENG2": "",
   "DTVAL_CO": 145803
 },
 {
   "TBL_ID": "DT_NSO_1001_021V1",
   "Period": 2019,
   "CODE": 26410,
   "SCR_MN": "Баянговь",
   "SCR_ENG": "Bayangovi",
   "CODE1": 1,
   "SCR_MN1": "Бүгд",
   "SCR_ENG1": "Total",
   "CODE2": "",
   "SCR_MN2": "",
   "SCR_ENG2": "",
   "DTVAL_CO": 230492
 },
 {
   "TBL_ID": "DT_NSO_1001_021V1",
   "Period": 2019,
   "CODE": 26413,
   "SCR_MN": "Баянлиг",
   "SCR_ENG": "Bayanlig",
   "CODE1": 1,
   "SCR_MN1": "Бүгд",
   "SCR_ENG1": "Total",
   "CODE2": "",
   "SCR_MN2": "",
   "SCR_ENG2": "",
   "DTVAL_CO": 248967
 },
 {
   "TBL_ID": "DT_NSO_1001_021V1",
   "Period": 2019,
   "CODE": 26416,
   "SCR_MN": "Баян-Овоо",
   "SCR_ENG": "Bayan-Ovoo",
   "CODE1": 1,
   "SCR_MN1": "Бүгд",
   "SCR_ENG1": "Total",
   "CODE2": "",
   "SCR_MN2": "",
   "SCR_ENG2": "",
   "DTVAL_CO": 272495
 },
 {
   "TBL_ID": "DT_NSO_1001_021V1",
   "Period": 2019,
   "CODE": 26419,
   "SCR_MN": "Баян-Өндөр",
   "SCR_ENG": "Bayan-Undur",
   "CODE1": 1,
   "SCR_MN1": "Бүгд",
   "SCR_ENG1": "Total",
   "CODE2": "",
   "SCR_MN2": "",
   "SCR_ENG2": "",
   "DTVAL_CO": 163699
 },
 {
   "TBL_ID": "DT_NSO_1001_021V1",
   "Period": 2019,
   "CODE": 26422,
   "SCR_MN": "Баянцагаан",
   "SCR_ENG": "Bayantsagaan",
   "CODE1": 1,
   "SCR_MN1": "Бүгд",
   "SCR_ENG1": "Total",
   "CODE2": "",
   "SCR_MN2": "",
   "SCR_ENG2": "",
   "DTVAL_CO": 255757
 },
 {
   "TBL_ID": "DT_NSO_1001_021V1",
   "Period": 2019,
   "CODE": 26425,
   "SCR_MN": "Богд",
   "SCR_ENG": "Bogd",
   "CODE1": 1,
   "SCR_MN1": "Бүгд",
   "SCR_ENG1": "Total",
   "CODE2": "",
   "SCR_MN2": "",
   "SCR_ENG2": "",
   "DTVAL_CO": 223739
 },
 {
   "TBL_ID": "DT_NSO_1001_021V1",
   "Period": 2019,
   "CODE": 26428,
   "SCR_MN": "Бөмбөгөр",
   "SCR_ENG": "Bumbugur",
   "CODE1": 1,
   "SCR_MN1": "Бүгд",
   "SCR_ENG1": "Total",
   "CODE2": "",
   "SCR_MN2": "",
   "SCR_ENG2": "",
   "DTVAL_CO": 299649
 },
 {
   "TBL_ID": "DT_NSO_1001_021V1",
   "Period": 2019,
   "CODE": 26431,
   "SCR_MN": "Бууцагаан",
   "SCR_ENG": "Buutsagaan",
   "CODE1": 1,
   "SCR_MN1": "Бүгд",
   "SCR_ENG1": "Total",
   "CODE2": "",
   "SCR_MN2": "",
   "SCR_ENG2": "",
   "DTVAL_CO": 303083
 },
 {
   "TBL_ID": "DT_NSO_1001_021V1",
   "Period": 2019,
   "CODE": 26434,
   "SCR_MN": "Галуут",
   "SCR_ENG": "Galuut",
   "CODE1": 1,
   "SCR_MN1": "Бүгд",
   "SCR_ENG1": "Total",
   "CODE2": "",
   "SCR_MN2": "",
   "SCR_ENG2": "",
   "DTVAL_CO": 309597
 },
 {
   "TBL_ID": "DT_NSO_1001_021V1",
   "Period": 2019,
   "CODE": 26437,
   "SCR_MN": "Гурванбулаг",
   "SCR_ENG": "Gurvanbulag",
   "CODE1": 1,
   "SCR_MN1": "Бүгд",
   "SCR_ENG1": "Total",
   "CODE2": "",
   "SCR_MN2": "",
   "SCR_ENG2": "",
   "DTVAL_CO": 192713
 },
 {
   "TBL_ID": "DT_NSO_1001_021V1",
   "Period": 2019,
   "CODE": 26440,
   "SCR_MN": "Жаргалант",
   "SCR_ENG": "Jargalant",
   "CODE1": 1,
   "SCR_MN1": "Бүгд",
   "SCR_ENG1": "Total",
   "CODE2": "",
   "SCR_MN2": "",
   "SCR_ENG2": "",
   "DTVAL_CO": 177510
 },
 {
   "TBL_ID": "DT_NSO_1001_021V1",
   "Period": 2019,
   "CODE": 26443,
   "SCR_MN": "Жинст",
   "SCR_ENG": "Jinst",
   "CODE1": 1,
   "SCR_MN1": "Бүгд",
   "SCR_ENG1": "Total",
   "CODE2": "",
   "SCR_MN2": "",
   "SCR_ENG2": "",
   "DTVAL_CO": 207619
 },
 {
   "TBL_ID": "DT_NSO_1001_021V1",
   "Period": 2019,
   "CODE": 26446,
   "SCR_MN": "Заг",
   "SCR_ENG": "Zag",
   "CODE1": 1,
   "SCR_MN1": "Бүгд",
   "SCR_ENG1": "Total",
   "CODE2": "",
   "SCR_MN2": "",
   "SCR_ENG2": "",
   "DTVAL_CO": 167229
 },
 {
   "TBL_ID": "DT_NSO_1001_021V1",
   "Period": 2019,
   "CODE": 26449,
   "SCR_MN": "Өлзийт",
   "SCR_ENG": "Ulziit",
   "CODE1": 1,
   "SCR_MN1": "Бүгд",
   "SCR_ENG1": "Total",
   "CODE2": "",
   "SCR_MN2": "",
   "SCR_ENG2": "",
   "DTVAL_CO": 277458
 },
 {
   "TBL_ID": "DT_NSO_1001_021V1",
   "Period": 2019,
   "CODE": 26452,
   "SCR_MN": "Хүрээмарал",
   "SCR_ENG": "Khureemaral",
   "CODE1": 1,
   "SCR_MN1": "Бүгд",
   "SCR_ENG1": "Total",
   "CODE2": "",
   "SCR_MN2": "",
   "SCR_ENG2": "",
   "DTVAL_CO": 222467
 },
 {
   "TBL_ID": "DT_NSO_1001_021V1",
   "Period": 2019,
   "CODE": 26455,
   "SCR_MN": "Шинэжинст",
   "SCR_ENG": "Shinejinst",
   "CODE1": 1,
   "SCR_MN1": "Бүгд",
   "SCR_ENG1": "Total",
   "CODE2": "",
   "SCR_MN2": "",
   "SCR_ENG2": "",
   "DTVAL_CO": 191042
 },
 {
   "TBL_ID": "DT_NSO_1001_021V1",
   "Period": 2019,
   "CODE": 26458,
   "SCR_MN": "Эрдэнэцогт",
   "SCR_ENG": "Erdenetsogt",
   "CODE1": 1,
   "SCR_MN1": "Бүгд",
   "SCR_ENG1": "Total",
   "CODE2": "",
   "SCR_MN2": "",
   "SCR_ENG2": "",
   "DTVAL_CO": 211346
 },
 {
   "TBL_ID": "DT_NSO_1001_021V1",
   "Period": 2019,
   "CODE": 26501,
   "SCR_MN": "Эрдэнэбулган",
   "SCR_ENG": "Erdenebulgan",
   "CODE1": 1,
   "SCR_MN1": "Бүгд",
   "SCR_ENG1": "Total",
   "CODE2": "",
   "SCR_MN2": "",
   "SCR_ENG2": "",
   "DTVAL_CO": 247715
 },
 {
   "TBL_ID": "DT_NSO_1001_021V1",
   "Period": 2019,
   "CODE": 26504,
   "SCR_MN": "Батцэнгэл",
   "SCR_ENG": "Battsengel",
   "CODE1": 1,
   "SCR_MN1": "Бүгд",
   "SCR_ENG1": "Total",
   "CODE2": "",
   "SCR_MN2": "",
   "SCR_ENG2": "",
   "DTVAL_CO": 433728
 },
 {
   "TBL_ID": "DT_NSO_1001_021V1",
   "Period": 2019,
   "CODE": 26507,
   "SCR_MN": "Булган",
   "SCR_ENG": "Bulgan",
   "CODE1": 1,
   "SCR_MN1": "Бүгд",
   "SCR_ENG1": "Total",
   "CODE2": "",
   "SCR_MN2": "",
   "SCR_ENG2": "",
   "DTVAL_CO": 158327
 },
 {
   "TBL_ID": "DT_NSO_1001_021V1",
   "Period": 2019,
   "CODE": 26510,
   "SCR_MN": "Жаргалант",
   "SCR_ENG": "Jargalant",
   "CODE1": 1,
   "SCR_MN1": "Бүгд",
   "SCR_ENG1": "Total",
   "CODE2": "",
   "SCR_MN2": "",
   "SCR_ENG2": "",
   "DTVAL_CO": 286541
 },
 {
   "TBL_ID": "DT_NSO_1001_021V1",
   "Period": 2019,
   "CODE": 26513,
   "SCR_MN": "Их тамир",
   "SCR_ENG": "Ikh tamir",
   "CODE1": 1,
   "SCR_MN1": "Бүгд",
   "SCR_ENG1": "Total",
   "CODE2": "",
   "SCR_MN2": "",
   "SCR_ENG2": "",
   "DTVAL_CO": 403263
 },
 {
   "TBL_ID": "DT_NSO_1001_021V1",
   "Period": 2019,
   "CODE": 26516,
   "SCR_MN": "Өгийнуур",
   "SCR_ENG": "Ugiinuur",
   "CODE1": 1,
   "SCR_MN1": "Бүгд",
   "SCR_ENG1": "Total",
   "CODE2": "",
   "SCR_MN2": "",
   "SCR_ENG2": "",
   "DTVAL_CO": 324463
 },
 {
   "TBL_ID": "DT_NSO_1001_021V1",
   "Period": 2019,
   "CODE": 26519,
   "SCR_MN": "Өлзийт",
   "SCR_ENG": "Ulziit",
   "CODE1": 1,
   "SCR_MN1": "Бүгд",
   "SCR_ENG1": "Total",
   "CODE2": "",
   "SCR_MN2": "",
   "SCR_ENG2": "",
   "DTVAL_CO": 353240
 },
 {
   "TBL_ID": "DT_NSO_1001_021V1",
   "Period": 2019,
   "CODE": 26522,
   "SCR_MN": "Өндөр-Улаан",
   "SCR_ENG": "Undur-Ulaan",
   "CODE1": 1,
   "SCR_MN1": "Бүгд",
   "SCR_ENG1": "Total",
   "CODE2": "",
   "SCR_MN2": "",
   "SCR_ENG2": "",
   "DTVAL_CO": 406349
 },
 {
   "TBL_ID": "DT_NSO_1001_021V1",
   "Period": 2019,
   "CODE": 26525,
   "SCR_MN": "Тариат",
   "SCR_ENG": "Tariat",
   "CODE1": 1,
   "SCR_MN1": "Бүгд",
   "SCR_ENG1": "Total",
   "CODE2": "",
   "SCR_MN2": "",
   "SCR_ENG2": "",
   "DTVAL_CO": 333785
 },
 {
   "TBL_ID": "DT_NSO_1001_021V1",
   "Period": 2019,
   "CODE": 26528,
   "SCR_MN": "Төвшрүүлэх",
   "SCR_ENG": "Tuvshruulekh",
   "CODE1": 1,
   "SCR_MN1": "Бүгд",
   "SCR_ENG1": "Total",
   "CODE2": "",
   "SCR_MN2": "",
   "SCR_ENG2": "",
   "DTVAL_CO": 180771
 },
 {
   "TBL_ID": "DT_NSO_1001_021V1",
   "Period": 2019,
   "CODE": 26531,
   "SCR_MN": "Хайрхан",
   "SCR_ENG": "2-r bag, Khairkhan",
   "CODE1": 1,
   "SCR_MN1": "Бүгд",
   "SCR_ENG1": "Total",
   "CODE2": "",
   "SCR_MN2": "",
   "SCR_ENG2": "",
   "DTVAL_CO": 453548
 },
 {
   "TBL_ID": "DT_NSO_1001_021V1",
   "Period": 2019,
   "CODE": 26534,
   "SCR_MN": "Хангайн бүс",
   "SCR_ENG": "Khangai region",
   "CODE1": 1,
   "SCR_MN1": "Бүгд",
   "SCR_ENG1": "Total",
   "CODE2": "",
   "SCR_MN2": "",
   "SCR_ENG2": "",
   "DTVAL_CO": 134970
 },
 {
   "TBL_ID": "DT_NSO_1001_021V1",
   "Period": 2019,
   "CODE": 26537,
   "SCR_MN": "Хашаат",
   "SCR_ENG": "Khashaat",
   "CODE1": 1,
   "SCR_MN1": "Бүгд",
   "SCR_ENG1": "Total",
   "CODE2": "",
   "SCR_MN2": "",
   "SCR_ENG2": "",
   "DTVAL_CO": 372291
 },
 {
   "TBL_ID": "DT_NSO_1001_021V1",
   "Period": 2019,
   "CODE": 26540,
   "SCR_MN": "Хотонт",
   "SCR_ENG": "Khotont",
   "CODE1": 1,
   "SCR_MN1": "Бүгд",
   "SCR_ENG1": "Total",
   "CODE2": "",
   "SCR_MN2": "",
   "SCR_ENG2": "",
   "DTVAL_CO": 398727
 },
 {
   "TBL_ID": "DT_NSO_1001_021V1",
   "Period": 2019,
   "CODE": 26543,
   "SCR_MN": "Цахир",
   "SCR_ENG": "Tsakhir",
   "CODE1": 1,
   "SCR_MN1": "Бүгд",
   "SCR_ENG1": "Total",
   "CODE2": "",
   "SCR_MN2": "",
   "SCR_ENG2": "",
   "DTVAL_CO": 140425
 },
 {
   "TBL_ID": "DT_NSO_1001_021V1",
   "Period": 2019,
   "CODE": 26546,
   "SCR_MN": "Цэнхэр",
   "SCR_ENG": "Tsenkher",
   "CODE1": 1,
   "SCR_MN1": "Бүгд",
   "SCR_ENG1": "Total",
   "CODE2": "",
   "SCR_MN2": "",
   "SCR_ENG2": "",
   "DTVAL_CO": 372685
 },
 {
   "TBL_ID": "DT_NSO_1001_021V1",
   "Period": 2019,
   "CODE": 26549,
   "SCR_MN": "Цэцэрлэг",
   "SCR_ENG": "Tsetserleg",
   "CODE1": 1,
   "SCR_MN1": "Бүгд",
   "SCR_ENG1": "Total",
   "CODE2": "",
   "SCR_MN2": "",
   "SCR_ENG2": "",
   "DTVAL_CO": 382062
 },
 {
   "TBL_ID": "DT_NSO_1001_021V1",
   "Period": 2019,
   "CODE": 26552,
   "SCR_MN": "Чулуут",
   "SCR_ENG": "Chuluut",
   "CODE1": 1,
   "SCR_MN1": "Бүгд",
   "SCR_ENG1": "Total",
   "CODE2": "",
   "SCR_MN2": "",
   "SCR_ENG2": "",
   "DTVAL_CO": 225653
 },
 {
   "TBL_ID": "DT_NSO_1001_021V1",
   "Period": 2019,
   "CODE": 26555,
   "SCR_MN": "Эрдэнэмандал",
   "SCR_ENG": "Erdenemandal",
   "CODE1": 1,
   "SCR_MN1": "Бүгд",
   "SCR_ENG1": "Total",
   "CODE2": "",
   "SCR_MN2": "",
   "SCR_ENG2": "",
   "DTVAL_CO": 558493
 },
 {
   "TBL_ID": "DT_NSO_1001_021V1",
   "Period": 2019,
   "CODE": 26701,
   "SCR_MN": "Мөрөн",
   "SCR_ENG": "Murun",
   "CODE1": 1,
   "SCR_MN1": "Бүгд",
   "SCR_ENG1": "Total",
   "CODE2": "",
   "SCR_MN2": "",
   "SCR_ENG2": "",
   "DTVAL_CO": 249815
 },
 {
   "TBL_ID": "DT_NSO_1001_021V1",
   "Period": 2019,
   "CODE": 26704,
   "SCR_MN": "Алаг-Эрдэнэ",
   "SCR_ENG": "Alag-Erdene",
   "CODE1": 1,
   "SCR_MN1": "Бүгд",
   "SCR_ENG1": "Total",
   "CODE2": "",
   "SCR_MN2": "",
   "SCR_ENG2": "",
   "DTVAL_CO": 298716
 },
 {
   "TBL_ID": "DT_NSO_1001_021V1",
   "Period": 2019,
   "CODE": 26707,
   "SCR_MN": "Арбулаг",
   "SCR_ENG": "Arbulag",
   "CODE1": 1,
   "SCR_MN1": "Бүгд",
   "SCR_ENG1": "Total",
   "CODE2": "",
   "SCR_MN2": "",
   "SCR_ENG2": "",
   "DTVAL_CO": 418459
 },
 {
   "TBL_ID": "DT_NSO_1001_021V1",
   "Period": 2019,
   "CODE": 26710,
   "SCR_MN": "Баянзүрх",
   "SCR_ENG": "Bayanzurkh",
   "CODE1": 1,
   "SCR_MN1": "Бүгд",
   "SCR_ENG1": "Total",
   "CODE2": "",
   "SCR_MN2": "",
   "SCR_ENG2": "",
   "DTVAL_CO": 342381
 },
 {
   "TBL_ID": "DT_NSO_1001_021V1",
   "Period": 2019,
   "CODE": 26713,
   "SCR_MN": "Бүрэнтогтох",
   "SCR_ENG": "Burentogtokh",
   "CODE1": 1,
   "SCR_MN1": "Бүгд",
   "SCR_ENG1": "Total",
   "CODE2": "",
   "SCR_MN2": "",
   "SCR_ENG2": "",
   "DTVAL_CO": 436067
 },
 {
   "TBL_ID": "DT_NSO_1001_021V1",
   "Period": 2019,
   "CODE": 26716,
   "SCR_MN": "Галт",
   "SCR_ENG": "Galt",
   "CODE1": 1,
   "SCR_MN1": "Бүгд",
   "SCR_ENG1": "Total",
   "CODE2": "",
   "SCR_MN2": "",
   "SCR_ENG2": "",
   "DTVAL_CO": 406366
 },
 {
   "TBL_ID": "DT_NSO_1001_021V1",
   "Period": 2019,
   "CODE": 26719,
   "SCR_MN": "Жаргалант",
   "SCR_ENG": "Jargalant",
   "CODE1": 1,
   "SCR_MN1": "Бүгд",
   "SCR_ENG1": "Total",
   "CODE2": "",
   "SCR_MN2": "",
   "SCR_ENG2": "",
   "DTVAL_CO": 293231
 },
 {
   "TBL_ID": "DT_NSO_1001_021V1",
   "Period": 2019,
   "CODE": 26722,
   "SCR_MN": "Их-Уул",
   "SCR_ENG": "Ikh-Uul",
   "CODE1": 1,
   "SCR_MN1": "Бүгд",
   "SCR_ENG1": "Total",
   "CODE2": "",
   "SCR_MN2": "",
   "SCR_ENG2": "",
   "DTVAL_CO": 318689
 },
 {
   "TBL_ID": "DT_NSO_1001_021V1",
   "Period": 2019,
   "CODE": 26725,
   "SCR_MN": "Рашаант",
   "SCR_ENG": "Rashaant",
   "CODE1": 1,
   "SCR_MN1": "Бүгд",
   "SCR_ENG1": "Total",
   "CODE2": "",
   "SCR_MN2": "",
   "SCR_ENG2": "",
   "DTVAL_CO": 253153
 },
 {
   "TBL_ID": "DT_NSO_1001_021V1",
   "Period": 2019,
   "CODE": 26728,
   "SCR_MN": "Рэнчинлхүмбэ",
   "SCR_ENG": "Renchinlkhumbe",
   "CODE1": 1,
   "SCR_MN1": "Бүгд",
   "SCR_ENG1": "Total",
   "CODE2": "",
   "SCR_MN2": "",
   "SCR_ENG2": "",
   "DTVAL_CO": 216061
 },
 {
   "TBL_ID": "DT_NSO_1001_021V1",
   "Period": 2019,
   "CODE": 26731,
   "SCR_MN": "Тариалан",
   "SCR_ENG": "Tarialan",
   "CODE1": 1,
   "SCR_MN1": "Бүгд",
   "SCR_ENG1": "Total",
   "CODE2": "",
   "SCR_MN2": "",
   "SCR_ENG2": "",
   "DTVAL_CO": 254106
 },
 {
   "TBL_ID": "DT_NSO_1001_021V1",
   "Period": 2019,
   "CODE": 26734,
   "SCR_MN": "Тосонцэнгэл",
   "SCR_ENG": "Tosontsengel",
   "CODE1": 1,
   "SCR_MN1": "Бүгд",
   "SCR_ENG1": "Total",
   "CODE2": "",
   "SCR_MN2": "",
   "SCR_ENG2": "",
   "DTVAL_CO": 361128
 },
 {
   "TBL_ID": "DT_NSO_1001_021V1",
   "Period": 2019,
   "CODE": 26737,
   "SCR_MN": "Төмөрбулаг",
   "SCR_ENG": "Tumurbulag",
   "CODE1": 1,
   "SCR_MN1": "Бүгд",
   "SCR_ENG1": "Total",
   "CODE2": "",
   "SCR_MN2": "",
   "SCR_ENG2": "",
   "DTVAL_CO": 376694
 },
 {
   "TBL_ID": "DT_NSO_1001_021V1",
   "Period": 2019,
   "CODE": 26740,
   "SCR_MN": "Түнэл",
   "SCR_ENG": "Tunel",
   "CODE1": 1,
   "SCR_MN1": "Бүгд",
   "SCR_ENG1": "Total",
   "CODE2": "",
   "SCR_MN2": "",
   "SCR_ENG2": "",
   "DTVAL_CO": 304434
 },
 {
   "TBL_ID": "DT_NSO_1001_021V1",
   "Period": 2019,
   "CODE": 26743,
   "SCR_MN": "Улаан-Уул",
   "SCR_ENG": "Ulaan-Uul",
   "CODE1": 1,
   "SCR_MN1": "Бүгд",
   "SCR_ENG1": "Total",
   "CODE2": "",
   "SCR_MN2": "",
   "SCR_ENG2": "",
   "DTVAL_CO": 207044
 },
 {
   "TBL_ID": "DT_NSO_1001_021V1",
   "Period": 2019,
   "CODE": 26746,
   "SCR_MN": "Ханх",
   "SCR_ENG": "Khankh",
   "CODE1": 1,
   "SCR_MN1": "Бүгд",
   "SCR_ENG1": "Total",
   "CODE2": "",
   "SCR_MN2": "",
   "SCR_ENG2": "",
   "DTVAL_CO": 54562
 },
 {
   "TBL_ID": "DT_NSO_1001_021V1",
   "Period": 2019,
   "CODE": 26749,
   "SCR_MN": "Цагааннуур",
   "SCR_ENG": "Tsagaannuur",
   "CODE1": 1,
   "SCR_MN1": "Бүгд",
   "SCR_ENG1": "Total",
   "CODE2": "",
   "SCR_MN2": "",
   "SCR_ENG2": "",
   "DTVAL_CO": 21843
 },
 {
   "TBL_ID": "DT_NSO_1001_021V1",
   "Period": 2019,
   "CODE": 26752,
   "SCR_MN": "Цагаан-Уул",
   "SCR_ENG": "Tsagaan-Uul",
   "CODE1": 1,
   "SCR_MN1": "Бүгд",
   "SCR_ENG1": "Total",
   "CODE2": "",
   "SCR_MN2": "",
   "SCR_ENG2": "",
   "DTVAL_CO": 479781
 },
 {
   "TBL_ID": "DT_NSO_1001_021V1",
   "Period": 2019,
   "CODE": 26755,
   "SCR_MN": "Цагаан-Үүр",
   "SCR_ENG": "Tsagaan-Uur",
   "CODE1": 1,
   "SCR_MN1": "Бүгд",
   "SCR_ENG1": "Total",
   "CODE2": "",
   "SCR_MN2": "",
   "SCR_ENG2": "",
   "DTVAL_CO": 33257
 },
 {
   "TBL_ID": "DT_NSO_1001_021V1",
   "Period": 2019,
   "CODE": 26758,
   "SCR_MN": "Цэцэрлэг",
   "SCR_ENG": "Tsetserleg",
   "CODE1": 1,
   "SCR_MN1": "Бүгд",
   "SCR_ENG1": "Total",
   "CODE2": "",
   "SCR_MN2": "",
   "SCR_ENG2": "",
   "DTVAL_CO": 308596
 },
 {
   "TBL_ID": "DT_NSO_1001_021V1",
   "Period": 2019,
   "CODE": 26761,
   "SCR_MN": "Чандмань-Өндөр",
   "SCR_ENG": "Chandmani-Undur",
   "CODE1": 1,
   "SCR_MN1": "Бүгд",
   "SCR_ENG1": "Total",
   "CODE2": "",
   "SCR_MN2": "",
   "SCR_ENG2": "",
   "DTVAL_CO": 71908
 },
 {
   "TBL_ID": "DT_NSO_1001_021V1",
   "Period": 2019,
   "CODE": 26764,
   "SCR_MN": "Шинэ-Идэр",
   "SCR_ENG": "Shine-Ider",
   "CODE1": 1,
   "SCR_MN1": "Бүгд",
   "SCR_ENG1": "Total",
   "CODE2": "",
   "SCR_MN2": "",
   "SCR_ENG2": "",
   "DTVAL_CO": 232526
 },
 {
   "TBL_ID": "DT_NSO_1001_021V1",
   "Period": 2019,
   "CODE": 26767,
   "SCR_MN": "Эрдэнэбулган",
   "SCR_ENG": "Erdenebulgan",
   "CODE1": 1,
   "SCR_MN1": "Бүгд",
   "SCR_ENG1": "Total",
   "CODE2": "",
   "SCR_MN2": "",
   "SCR_ENG2": "",
   "DTVAL_CO": 101614
 },
 {
   "TBL_ID": "DT_NSO_1001_021V1",
   "Period": 2019,
   "CODE": 34101,
   "SCR_MN": "Зуунмод",
   "SCR_ENG": "Zuunmod",
   "CODE1": 1,
   "SCR_MN1": "Бүгд",
   "SCR_ENG1": "Total",
   "CODE2": "",
   "SCR_MN2": "",
   "SCR_ENG2": "",
   "DTVAL_CO": 89992
 },
 {
   "TBL_ID": "DT_NSO_1001_021V1",
   "Period": 2019,
   "CODE": 34104,
   "SCR_MN": "Алтанбулаг",
   "SCR_ENG": "Altanbulag",
   "CODE1": 1,
   "SCR_MN1": "Бүгд",
   "SCR_ENG1": "Total",
   "CODE2": "",
   "SCR_MN2": "",
   "SCR_ENG2": "",
   "DTVAL_CO": 331646
 },
 {
   "TBL_ID": "DT_NSO_1001_021V1",
   "Period": 2019,
   "CODE": 34107,
   "SCR_MN": "Аргалант",
   "SCR_ENG": "Argalant",
   "CODE1": 1,
   "SCR_MN1": "Бүгд",
   "SCR_ENG1": "Total",
   "CODE2": "",
   "SCR_MN2": "",
   "SCR_ENG2": "",
   "DTVAL_CO": 95513
 },
 {
   "TBL_ID": "DT_NSO_1001_021V1",
   "Period": 2019,
   "CODE": 34110,
   "SCR_MN": "Архуст",
   "SCR_ENG": "Arkhust",
   "CODE1": 1,
   "SCR_MN1": "Бүгд",
   "SCR_ENG1": "Total",
   "CODE2": "",
   "SCR_MN2": "",
   "SCR_ENG2": "",
   "DTVAL_CO": 66789
 },
 {
   "TBL_ID": "DT_NSO_1001_021V1",
   "Period": 2019,
   "CODE": 34113,
   "SCR_MN": "Батсүмбэр",
   "SCR_ENG": "Batsumber",
   "CODE1": 1,
   "SCR_MN1": "Бүгд",
   "SCR_ENG1": "Total",
   "CODE2": "",
   "SCR_MN2": "",
   "SCR_ENG2": "",
   "DTVAL_CO": 71211
 },
 {
   "TBL_ID": "DT_NSO_1001_021V1",
   "Period": 2019,
   "CODE": 34116,
   "SCR_MN": "Баян",
   "SCR_ENG": "Bayan",
   "CODE1": 1,
   "SCR_MN1": "Бүгд",
   "SCR_ENG1": "Total",
   "CODE2": "",
   "SCR_MN2": "",
   "SCR_ENG2": "",
   "DTVAL_CO": 159767
 },
 {
   "TBL_ID": "DT_NSO_1001_021V1",
   "Period": 2019,
   "CODE": 34119,
   "SCR_MN": "Баяндэлгэр",
   "SCR_ENG": "Bayandelger",
   "CODE1": 1,
   "SCR_MN1": "Бүгд",
   "SCR_ENG1": "Total",
   "CODE2": "",
   "SCR_MN2": "",
   "SCR_ENG2": "",
   "DTVAL_CO": 212041
 },
 {
   "TBL_ID": "DT_NSO_1001_021V1",
   "Period": 2019,
   "CODE": 34122,
   "SCR_MN": "Баянжаргалан",
   "SCR_ENG": "Bayanjargalan",
   "CODE1": 1,
   "SCR_MN1": "Бүгд",
   "SCR_ENG1": "Total",
   "CODE2": "",
   "SCR_MN2": "",
   "SCR_ENG2": "",
   "DTVAL_CO": 213070
 },
 {
   "TBL_ID": "DT_NSO_1001_021V1",
   "Period": 2019,
   "CODE": 34125,
   "SCR_MN": "Баян-Өнжүүл",
   "SCR_ENG": "Bayan-Unjuul",
   "CODE1": 1,
   "SCR_MN1": "Бүгд",
   "SCR_ENG1": "Total",
   "CODE2": "",
   "SCR_MN2": "",
   "SCR_ENG2": "",
   "DTVAL_CO": 364424
 },
 {
   "TBL_ID": "DT_NSO_1001_021V1",
   "Period": 2019,
   "CODE": 34128,
   "SCR_MN": "Баянхангай",
   "SCR_ENG": "Bayankhangai",
   "CODE1": 1,
   "SCR_MN1": "Бүгд",
   "SCR_ENG1": "Total",
   "CODE2": "",
   "SCR_MN2": "",
   "SCR_ENG2": "",
   "DTVAL_CO": 88457
 },
 {
   "TBL_ID": "DT_NSO_1001_021V1",
   "Period": 2019,
   "CODE": 34131,
   "SCR_MN": "Баянцагаан",
   "SCR_ENG": "Bayantsagaan",
   "CODE1": 1,
   "SCR_MN1": "Бүгд",
   "SCR_ENG1": "Total",
   "CODE2": "",
   "SCR_MN2": "",
   "SCR_ENG2": "",
   "DTVAL_CO": 298769
 },
 {
   "TBL_ID": "DT_NSO_1001_021V1",
   "Period": 2019,
   "CODE": 34134,
   "SCR_MN": "Баянцогт",
   "SCR_ENG": "Bayantsogt",
   "CODE1": 1,
   "SCR_MN1": "Бүгд",
   "SCR_ENG1": "Total",
   "CODE2": "",
   "SCR_MN2": "",
   "SCR_ENG2": "",
   "DTVAL_CO": 104998
 },
 {
   "TBL_ID": "DT_NSO_1001_021V1",
   "Period": 2019,
   "CODE": 34137,
   "SCR_MN": "Баянчандмань",
   "SCR_ENG": "Bayanchandmani",
   "CODE1": 1,
   "SCR_MN1": "Бүгд",
   "SCR_ENG1": "Total",
   "CODE2": "",
   "SCR_MN2": "",
   "SCR_ENG2": "",
   "DTVAL_CO": 44422
 },
 {
   "TBL_ID": "DT_NSO_1001_021V1",
   "Period": 2019,
   "CODE": 34140,
   "SCR_MN": "Борнуур",
   "SCR_ENG": "Bornuur",
   "CODE1": 1,
   "SCR_MN1": "Бүгд",
   "SCR_ENG1": "Total",
   "CODE2": "",
   "SCR_MN2": "",
   "SCR_ENG2": "",
   "DTVAL_CO": 101860
 },
 {
   "TBL_ID": "DT_NSO_1001_021V1",
   "Period": 2019,
   "CODE": 34143,
   "SCR_MN": "Бүрэн",
   "SCR_ENG": "Buren",
   "CODE1": 1,
   "SCR_MN1": "Бүгд",
   "SCR_ENG1": "Total",
   "CODE2": "",
   "SCR_MN2": "",
   "SCR_ENG2": "",
   "DTVAL_CO": 346607
 },
 {
   "TBL_ID": "DT_NSO_1001_021V1",
   "Period": 2019,
   "CODE": 34146,
   "SCR_MN": "Дэлгэрхаан",
   "SCR_ENG": "Delgerkhaan",
   "CODE1": 1,
   "SCR_MN1": "Бүгд",
   "SCR_ENG1": "Total",
   "CODE2": "",
   "SCR_MN2": "",
   "SCR_ENG2": "",
   "DTVAL_CO": 200727
 },
 {
   "TBL_ID": "DT_NSO_1001_021V1",
   "Period": 2019,
   "CODE": 34149,
   "SCR_MN": "Жаргалант",
   "SCR_ENG": "Jargalant",
   "CODE1": 1,
   "SCR_MN1": "Бүгд",
   "SCR_ENG1": "Total",
   "CODE2": "",
   "SCR_MN2": "",
   "SCR_ENG2": "",
   "DTVAL_CO": 160934
 },
 {
   "TBL_ID": "DT_NSO_1001_021V1",
   "Period": 2019,
   "CODE": 34152,
   "SCR_MN": "Заамар",
   "SCR_ENG": "Zaamar",
   "CODE1": 1,
   "SCR_MN1": "Бүгд",
   "SCR_ENG1": "Total",
   "CODE2": "",
   "SCR_MN2": "",
   "SCR_ENG2": "",
   "DTVAL_CO": 241095
 },
 {
   "TBL_ID": "DT_NSO_1001_021V1",
   "Period": 2019,
   "CODE": 34155,
   "SCR_MN": "Лүн",
   "SCR_ENG": "Lun",
   "CODE1": 1,
   "SCR_MN1": "Бүгд",
   "SCR_ENG1": "Total",
   "CODE2": "",
   "SCR_MN2": "",
   "SCR_ENG2": "",
   "DTVAL_CO": 265453
 },
 {
   "TBL_ID": "DT_NSO_1001_021V1",
   "Period": 2019,
   "CODE": 34158,
   "SCR_MN": "Мөнгөнморьт",
   "SCR_ENG": "Mungunmorit",
   "CODE1": 1,
   "SCR_MN1": "Бүгд",
   "SCR_ENG1": "Total",
   "CODE2": "",
   "SCR_MN2": "",
   "SCR_ENG2": "",
   "DTVAL_CO": 102363
 },
 {
   "TBL_ID": "DT_NSO_1001_021V1",
   "Period": 2019,
   "CODE": 34161,
   "SCR_MN": "Өндөрширээт",
   "SCR_ENG": "Undurshireet",
   "CODE1": 1,
   "SCR_MN1": "Бүгд",
   "SCR_ENG1": "Total",
   "CODE2": "",
   "SCR_MN2": "",
   "SCR_ENG2": "",
   "DTVAL_CO": 276370
 },
 {
   "TBL_ID": "DT_NSO_1001_021V1",
   "Period": 2019,
   "CODE": 34164,
   "SCR_MN": "Сүмбэр",
   "SCR_ENG": "Sumber",
   "CODE1": 1,
   "SCR_MN1": "Бүгд",
   "SCR_ENG1": "Total",
   "CODE2": "",
   "SCR_MN2": "",
   "SCR_ENG2": "",
   "DTVAL_CO": 43202
 },
 {
   "TBL_ID": "DT_NSO_1001_021V1",
   "Period": 2019,
   "CODE": 34167,
   "SCR_MN": "Сэргэлэн",
   "SCR_ENG": "Sergelen",
   "CODE1": 1,
   "SCR_MN1": "Бүгд",
   "SCR_ENG1": "Total",
   "CODE2": "",
   "SCR_MN2": "",
   "SCR_ENG2": "",
   "DTVAL_CO": 173696
 },
 {
   "TBL_ID": "DT_NSO_1001_021V1",
   "Period": 2019,
   "CODE": 34170,
   "SCR_MN": "Угтаалцайдам",
   "SCR_ENG": "Ugtaaltsaidam",
   "CODE1": 1,
   "SCR_MN1": "Бүгд",
   "SCR_ENG1": "Total",
   "CODE2": "",
   "SCR_MN2": "",
   "SCR_ENG2": "",
   "DTVAL_CO": 125434
 },
 {
   "TBL_ID": "DT_NSO_1001_021V1",
   "Period": 2019,
   "CODE": 34173,
   "SCR_MN": "Цээл",
   "SCR_ENG": "Tseel",
   "CODE1": 1,
   "SCR_MN1": "Бүгд",
   "SCR_ENG1": "Total",
   "CODE2": "",
   "SCR_MN2": "",
   "SCR_ENG2": "",
   "DTVAL_CO": 136196
 },
 {
   "TBL_ID": "DT_NSO_1001_021V1",
   "Period": 2019,
   "CODE": 34176,
   "SCR_MN": "Эрдэнэ",
   "SCR_ENG": "Erdene",
   "CODE1": 1,
   "SCR_MN1": "Бүгд",
   "SCR_ENG1": "Total",
   "CODE2": "",
   "SCR_MN2": "",
   "SCR_ENG2": "",
   "DTVAL_CO": 223595
 },
 {
   "TBL_ID": "DT_NSO_1001_021V1",
   "Period": 2019,
   "CODE": 34179,
   "SCR_MN": "Эрдэнэсант",
   "SCR_ENG": "Erdenesant",
   "CODE1": 1,
   "SCR_MN1": "Бүгд",
   "SCR_ENG1": "Total",
   "CODE2": "",
   "SCR_MN2": "",
   "SCR_ENG2": "",
   "DTVAL_CO": 440530
 },
 {
   "TBL_ID": "DT_NSO_1001_021V1",
   "Period": 2019,
   "CODE": 34201,
   "SCR_MN": "Сүмбэр",
   "SCR_ENG": "Sumber",
   "CODE1": 1,
   "SCR_MN1": "Бүгд",
   "SCR_ENG1": "Total",
   "CODE2": "",
   "SCR_MN2": "",
   "SCR_ENG2": "",
   "DTVAL_CO": 325928
 },
 {
   "TBL_ID": "DT_NSO_1001_021V1",
   "Period": 2019,
   "CODE": 34204,
   "SCR_MN": "Баянтал",
   "SCR_ENG": "Bayantal",
   "CODE1": 1,
   "SCR_MN1": "Бүгд",
   "SCR_ENG1": "Total",
   "CODE2": "",
   "SCR_MN2": "",
   "SCR_ENG2": "",
   "DTVAL_CO": 70684
 },
 {
   "TBL_ID": "DT_NSO_1001_021V1",
   "Period": 2019,
   "CODE": 34207,
   "SCR_MN": "Шивээговь",
   "SCR_ENG": "Shiveegovi",
   "CODE1": 1,
   "SCR_MN1": "Бүгд",
   "SCR_ENG1": "Total",
   "CODE2": "",
   "SCR_MN2": "",
   "SCR_ENG2": "",
   "DTVAL_CO": 55392
 },
 {
   "TBL_ID": "DT_NSO_1001_021V1",
   "Period": 2019,
   "CODE": 34301,
   "SCR_MN": "Сүхбаатар",
   "SCR_ENG": "Sukhbaatar",
   "CODE1": 1,
   "SCR_MN1": "Бүгд",
   "SCR_ENG1": "Total",
   "CODE2": "",
   "SCR_MN2": "",
   "SCR_ENG2": "",
   "DTVAL_CO": 23277
 },
 {
   "TBL_ID": "DT_NSO_1001_021V1",
   "Period": 2019,
   "CODE": 34304,
   "SCR_MN": "Алтанбулаг",
   "SCR_ENG": "Altanbulag",
   "CODE1": 1,
   "SCR_MN1": "Бүгд",
   "SCR_ENG1": "Total",
   "CODE2": "",
   "SCR_MN2": "",
   "SCR_ENG2": "",
   "DTVAL_CO": 61387
 },
 {
   "TBL_ID": "DT_NSO_1001_021V1",
   "Period": 2019,
   "CODE": 34307,
   "SCR_MN": "Баруунбүрэн",
   "SCR_ENG": "Baruunburen",
   "CODE1": 1,
   "SCR_MN1": "Бүгд",
   "SCR_ENG1": "Total",
   "CODE2": "",
   "SCR_MN2": "",
   "SCR_ENG2": "",
   "DTVAL_CO": 172573
 },
 {
   "TBL_ID": "DT_NSO_1001_021V1",
   "Period": 2019,
   "CODE": 34310,
   "SCR_MN": "Баянгол",
   "SCR_ENG": "Bayangol",
   "CODE1": 1,
   "SCR_MN1": "Бүгд",
   "SCR_ENG1": "Total",
   "CODE2": "",
   "SCR_MN2": "",
   "SCR_ENG2": "",
   "DTVAL_CO": 158157
 },
 {
   "TBL_ID": "DT_NSO_1001_021V1",
   "Period": 2019,
   "CODE": 34313,
   "SCR_MN": "Ерөө",
   "SCR_ENG": "Yeruu",
   "CODE1": 1,
   "SCR_MN1": "Бүгд",
   "SCR_ENG1": "Total",
   "CODE2": "",
   "SCR_MN2": "",
   "SCR_ENG2": "",
   "DTVAL_CO": 80598
 },
 {
   "TBL_ID": "DT_NSO_1001_021V1",
   "Period": 2019,
   "CODE": 34316,
   "SCR_MN": "Жавхлант",
   "SCR_ENG": "Javkhlant",
   "CODE1": 1,
   "SCR_MN1": "Бүгд",
   "SCR_ENG1": "Total",
   "CODE2": "",
   "SCR_MN2": "",
   "SCR_ENG2": "",
   "DTVAL_CO": 95410
 },
 {
   "TBL_ID": "DT_NSO_1001_021V1",
   "Period": 2019,
   "CODE": 34319,
   "SCR_MN": "Зүүнбүрэн",
   "SCR_ENG": "Zuunburen",
   "CODE1": 1,
   "SCR_MN1": "Бүгд",
   "SCR_ENG1": "Total",
   "CODE2": "",
   "SCR_MN2": "",
   "SCR_ENG2": "",
   "DTVAL_CO": 83231
 },
 {
   "TBL_ID": "DT_NSO_1001_021V1",
   "Period": 2019,
   "CODE": 34322,
   "SCR_MN": "Мандал",
   "SCR_ENG": "Mandal",
   "CODE1": 1,
   "SCR_MN1": "Бүгд",
   "SCR_ENG1": "Total",
   "CODE2": "",
   "SCR_MN2": "",
   "SCR_ENG2": "",
   "DTVAL_CO": 114199
 },
 {
   "TBL_ID": "DT_NSO_1001_021V1",
   "Period": 2019,
   "CODE": 34325,
   "SCR_MN": "Орхон",
   "SCR_ENG": "Orkhon",
   "CODE1": 1,
   "SCR_MN1": "Бүгд",
   "SCR_ENG1": "Total",
   "CODE2": "",
   "SCR_MN2": "",
   "SCR_ENG2": "",
   "DTVAL_CO": 105333
 },
 {
   "TBL_ID": "DT_NSO_1001_021V1",
   "Period": 2019,
   "CODE": 34328,
   "SCR_MN": "Орхонтуул",
   "SCR_ENG": "Orkhontuul",
   "CODE1": 1,
   "SCR_MN1": "Бүгд",
   "SCR_ENG1": "Total",
   "CODE2": "",
   "SCR_MN2": "",
   "SCR_ENG2": "",
   "DTVAL_CO": 212560
 },
 {
   "TBL_ID": "DT_NSO_1001_021V1",
   "Period": 2019,
   "CODE": 34331,
   "SCR_MN": "Сайхан",
   "SCR_ENG": "Saikhan",
   "CODE1": 1,
   "SCR_MN1": "Бүгд",
   "SCR_ENG1": "Total",
   "CODE2": "",
   "SCR_MN2": "",
   "SCR_ENG2": "",
   "DTVAL_CO": 105040
 },
 {
   "TBL_ID": "DT_NSO_1001_021V1",
   "Period": 2019,
   "CODE": 34334,
   "SCR_MN": "Сант",
   "SCR_ENG": "Sant",
   "CODE1": 1,
   "SCR_MN1": "Бүгд",
   "SCR_ENG1": "Total",
   "CODE2": "",
   "SCR_MN2": "",
   "SCR_ENG2": "",
   "DTVAL_CO": 85481
 },
 {
   "TBL_ID": "DT_NSO_1001_021V1",
   "Period": 2019,
   "CODE": 34337,
   "SCR_MN": "Түшиг",
   "SCR_ENG": "Tushig",
   "CODE1": 1,
   "SCR_MN1": "Бүгд",
   "SCR_ENG1": "Total",
   "CODE2": "",
   "SCR_MN2": "",
   "SCR_ENG2": "",
   "DTVAL_CO": 59470
 },
 {
   "TBL_ID": "DT_NSO_1001_021V1",
   "Period": 2019,
   "CODE": 34340,
   "SCR_MN": "Хүдэр",
   "SCR_ENG": "Khuder",
   "CODE1": 1,
   "SCR_MN1": "Бүгд",
   "SCR_ENG1": "Total",
   "CODE2": "",
   "SCR_MN2": "",
   "SCR_ENG2": "",
   "DTVAL_CO": 32460
 },
 {
   "TBL_ID": "DT_NSO_1001_021V1",
   "Period": 2019,
   "CODE": 34343,
   "SCR_MN": "Хушаат",
   "SCR_ENG": "Khushaat",
   "CODE1": 1,
   "SCR_MN1": "Бүгд",
   "SCR_ENG1": "Total",
   "CODE2": "",
   "SCR_MN2": "",
   "SCR_ENG2": "",
   "DTVAL_CO": 88504
 },
 {
   "TBL_ID": "DT_NSO_1001_021V1",
   "Period": 2019,
   "CODE": 34346,
   "SCR_MN": "Цагааннуур",
   "SCR_ENG": "Tsagaannuur",
   "CODE1": 1,
   "SCR_MN1": "Бүгд",
   "SCR_ENG1": "Total",
   "CODE2": "",
   "SCR_MN2": "",
   "SCR_ENG2": "",
   "DTVAL_CO": 179696
 },
 {
   "TBL_ID": "DT_NSO_1001_021V1",
   "Period": 2019,
   "CODE": 34349,
   "SCR_MN": "Шаамар",
   "SCR_ENG": "Shaamar",
   "CODE1": 1,
   "SCR_MN1": "Бүгд",
   "SCR_ENG1": "Total",
   "CODE2": "",
   "SCR_MN2": "",
   "SCR_ENG2": "",
   "DTVAL_CO": 25113
 },
 {
   "TBL_ID": "DT_NSO_1001_021V1",
   "Period": 2019,
   "CODE": 34401,
   "SCR_MN": "Сайншанд",
   "SCR_ENG": "Sainshand",
   "CODE1": 1,
   "SCR_MN1": "Бүгд",
   "SCR_ENG1": "Total",
   "CODE2": "",
   "SCR_MN2": "",
   "SCR_ENG2": "",
   "DTVAL_CO": 132113
 },
 {
   "TBL_ID": "DT_NSO_1001_021V1",
   "Period": 2019,
   "CODE": 34404,
   "SCR_MN": "Айраг",
   "SCR_ENG": "Airag",
   "CODE1": 1,
   "SCR_MN1": "Бүгд",
   "SCR_ENG1": "Total",
   "CODE2": "",
   "SCR_MN2": "",
   "SCR_ENG2": "",
   "DTVAL_CO": 183260
 },
 {
   "TBL_ID": "DT_NSO_1001_021V1",
   "Period": 2019,
   "CODE": 34407,
   "SCR_MN": "Алтанширээ",
   "SCR_ENG": "Altanshiree",
   "CODE1": 1,
   "SCR_MN1": "Бүгд",
   "SCR_ENG1": "Total",
   "CODE2": "",
   "SCR_MN2": "",
   "SCR_ENG2": "",
   "DTVAL_CO": 146936
 },
 {
   "TBL_ID": "DT_NSO_1001_021V1",
   "Period": 2019,
   "CODE": 34410,
   "SCR_MN": "Даланжаргалан",
   "SCR_ENG": "Dalanjargalan",
   "CODE1": 1,
   "SCR_MN1": "Бүгд",
   "SCR_ENG1": "Total",
   "CODE2": "",
   "SCR_MN2": "",
   "SCR_ENG2": "",
   "DTVAL_CO": 196772
 },
 {
   "TBL_ID": "DT_NSO_1001_021V1",
   "Period": 2019,
   "CODE": 34413,
   "SCR_MN": "Дэлгэрэх",
   "SCR_ENG": "Delgerekh",
   "CODE1": 1,
   "SCR_MN1": "Бүгд",
   "SCR_ENG1": "Total",
   "CODE2": "",
   "SCR_MN2": "",
   "SCR_ENG2": "",
   "DTVAL_CO": 233142
 },
 {
   "TBL_ID": "DT_NSO_1001_021V1",
   "Period": 2019,
   "CODE": 34416,
   "SCR_MN": "Замын-Үүд",
   "SCR_ENG": "Zamiin-Uud",
   "CODE1": 1,
   "SCR_MN1": "Бүгд",
   "SCR_ENG1": "Total",
   "CODE2": "",
   "SCR_MN2": "",
   "SCR_ENG2": "",
   "DTVAL_CO": 54340
 },
 {
   "TBL_ID": "DT_NSO_1001_021V1",
   "Period": 2019,
   "CODE": 34419,
   "SCR_MN": "Иххэт",
   "SCR_ENG": "Ikhkhet",
   "CODE1": 1,
   "SCR_MN1": "Бүгд",
   "SCR_ENG1": "Total",
   "CODE2": "",
   "SCR_MN2": "",
   "SCR_ENG2": "",
   "DTVAL_CO": 177059
 },
 {
   "TBL_ID": "DT_NSO_1001_021V1",
   "Period": 2019,
   "CODE": 34422,
   "SCR_MN": "Мандах",
   "SCR_ENG": "Mandakh",
   "CODE1": 1,
   "SCR_MN1": "Бүгд",
   "SCR_ENG1": "Total",
   "CODE2": "",
   "SCR_MN2": "",
   "SCR_ENG2": "",
   "DTVAL_CO": 189007
 },
 {
   "TBL_ID": "DT_NSO_1001_021V1",
   "Period": 2019,
   "CODE": 34425,
   "SCR_MN": "Өргөн",
   "SCR_ENG": "Urgun",
   "CODE1": 1,
   "SCR_MN1": "Бүгд",
   "SCR_ENG1": "Total",
   "CODE2": "",
   "SCR_MN2": "",
   "SCR_ENG2": "",
   "DTVAL_CO": 169925
 },
 {
   "TBL_ID": "DT_NSO_1001_021V1",
   "Period": 2019,
   "CODE": 34428,
   "SCR_MN": "Сайхандулаан",
   "SCR_ENG": "Saikhandulaan",
   "CODE1": 1,
   "SCR_MN1": "Бүгд",
   "SCR_ENG1": "Total",
   "CODE2": "",
   "SCR_MN2": "",
   "SCR_ENG2": "",
   "DTVAL_CO": 193077
 },
 {
   "TBL_ID": "DT_NSO_1001_021V1",
   "Period": 2019,
   "CODE": 34431,
   "SCR_MN": "Улаанбадрах",
   "SCR_ENG": "Ulaanbadrakh",
   "CODE1": 1,
   "SCR_MN1": "Бүгд",
   "SCR_ENG1": "Total",
   "CODE2": "",
   "SCR_MN2": "",
   "SCR_ENG2": "",
   "DTVAL_CO": 157347
 },
 {
   "TBL_ID": "DT_NSO_1001_021V1",
   "Period": 2019,
   "CODE": 34434,
   "SCR_MN": "Хатанбулаг",
   "SCR_ENG": "Khatanbulag",
   "CODE1": 1,
   "SCR_MN1": "Бүгд",
   "SCR_ENG1": "Total",
   "CODE2": "",
   "SCR_MN2": "",
   "SCR_ENG2": "",
   "DTVAL_CO": 260184
 },
 {
   "TBL_ID": "DT_NSO_1001_021V1",
   "Period": 2019,
   "CODE": 34437,
   "SCR_MN": "Хөвсгөл",
   "SCR_ENG": "Khuvsgul",
   "CODE1": 1,
   "SCR_MN1": "Бүгд",
   "SCR_ENG1": "Total",
   "CODE2": "",
   "SCR_MN2": "",
   "SCR_ENG2": "",
   "DTVAL_CO": 159144
 },
 {
   "TBL_ID": "DT_NSO_1001_021V1",
   "Period": 2019,
   "CODE": 34440,
   "SCR_MN": "Эрдэнэ",
   "SCR_ENG": "Erdene",
   "CODE1": 1,
   "SCR_MN1": "Бүгд",
   "SCR_ENG1": "Total",
   "CODE2": "",
   "SCR_MN2": "",
   "SCR_ENG2": "",
   "DTVAL_CO": 151943
 },
 {
   "TBL_ID": "DT_NSO_1001_021V1",
   "Period": 2019,
   "CODE": 34501,
   "SCR_MN": "Дархан",
   "SCR_ENG": "Darkhan",
   "CODE1": 1,
   "SCR_MN1": "Бүгд",
   "SCR_ENG1": "Total",
   "CODE2": "",
   "SCR_MN2": "",
   "SCR_ENG2": "",
   "DTVAL_CO": 76573
 },
 {
   "TBL_ID": "DT_NSO_1001_021V1",
   "Period": 2019,
   "CODE": 34504,
   "SCR_MN": "Орхон",
   "SCR_ENG": "Orkhon",
   "CODE1": 1,
   "SCR_MN1": "Бүгд",
   "SCR_ENG1": "Total",
   "CODE2": "",
   "SCR_MN2": "",
   "SCR_ENG2": "",
   "DTVAL_CO": 46220
 },
 {
   "TBL_ID": "DT_NSO_1001_021V1",
   "Period": 2019,
   "CODE": 34507,
   "SCR_MN": "Хонгор",
   "SCR_ENG": "Khongor",
   "CODE1": 1,
   "SCR_MN1": "Бүгд",
   "SCR_ENG1": "Total",
   "CODE2": "",
   "SCR_MN2": "",
   "SCR_ENG2": "",
   "DTVAL_CO": 191541
 },
 {
   "TBL_ID": "DT_NSO_1001_021V1",
   "Period": 2019,
   "CODE": 34510,
   "SCR_MN": "Шарын гол",
   "SCR_ENG": "Shariin gol",
   "CODE1": 1,
   "SCR_MN1": "Бүгд",
   "SCR_ENG1": "Total",
   "CODE2": "",
   "SCR_MN2": "",
   "SCR_ENG2": "",
   "DTVAL_CO": 33019
 },
 {
   "TBL_ID": "DT_NSO_1001_021V1",
   "Period": 2019,
   "CODE": 34601,
   "SCR_MN": "Даланзадгад",
   "SCR_ENG": "Dalanzadgad",
   "CODE1": 1,
   "SCR_MN1": "Бүгд",
   "SCR_ENG1": "Total",
   "CODE2": "",
   "SCR_MN2": "",
   "SCR_ENG2": "",
   "DTVAL_CO": 127112
 },
 {
   "TBL_ID": "DT_NSO_1001_021V1",
   "Period": 2019,
   "CODE": 34604,
   "SCR_MN": "Баяндалай",
   "SCR_ENG": "Bayandalai",
   "CODE1": 1,
   "SCR_MN1": "Бүгд",
   "SCR_ENG1": "Total",
   "CODE2": "",
   "SCR_MN2": "",
   "SCR_ENG2": "",
   "DTVAL_CO": 206404
 },
 {
   "TBL_ID": "DT_NSO_1001_021V1",
   "Period": 2019,
   "CODE": 34607,
   "SCR_MN": "Баян-Овоо",
   "SCR_ENG": "Bayan-Ovoo",
   "CODE1": 1,
   "SCR_MN1": "Бүгд",
   "SCR_ENG1": "Total",
   "CODE2": "",
   "SCR_MN2": "",
   "SCR_ENG2": "",
   "DTVAL_CO": 169701
 },
 {
   "TBL_ID": "DT_NSO_1001_021V1",
   "Period": 2019,
   "CODE": 34610,
   "SCR_MN": "Булган",
   "SCR_ENG": "Bulgan",
   "CODE1": 1,
   "SCR_MN1": "Бүгд",
   "SCR_ENG1": "Total",
   "CODE2": "",
   "SCR_MN2": "",
   "SCR_ENG2": "",
   "DTVAL_CO": 236711
 },
 {
   "TBL_ID": "DT_NSO_1001_021V1",
   "Period": 2019,
   "CODE": 34613,
   "SCR_MN": "Гурвантэс",
   "SCR_ENG": "Gurvantes",
   "CODE1": 1,
   "SCR_MN1": "Бүгд",
   "SCR_ENG1": "Total",
   "CODE2": "",
   "SCR_MN2": "",
   "SCR_ENG2": "",
   "DTVAL_CO": 225294
 },
 {
   "TBL_ID": "DT_NSO_1001_021V1",
   "Period": 2019,
   "CODE": 34616,
   "SCR_MN": "Мандал-Овоо",
   "SCR_ENG": "Mandal-Ovoo",
   "CODE1": 1,
   "SCR_MN1": "Бүгд",
   "SCR_ENG1": "Total",
   "CODE2": "",
   "SCR_MN2": "",
   "SCR_ENG2": "",
   "DTVAL_CO": 234072
 },
 {
   "TBL_ID": "DT_NSO_1001_021V1",
   "Period": 2019,
   "CODE": 34619,
   "SCR_MN": "Манлай",
   "SCR_ENG": "Manlai",
   "CODE1": 1,
   "SCR_MN1": "Бүгд",
   "SCR_ENG1": "Total",
   "CODE2": "",
   "SCR_MN2": "",
   "SCR_ENG2": "",
   "DTVAL_CO": 220673
 },
 {
   "TBL_ID": "DT_NSO_1001_021V1",
   "Period": 2019,
   "CODE": 34622,
   "SCR_MN": "Ноён",
   "SCR_ENG": "Noyon",
   "CODE1": 1,
   "SCR_MN1": "Бүгд",
   "SCR_ENG1": "Total",
   "CODE2": "",
   "SCR_MN2": "",
   "SCR_ENG2": "",
   "DTVAL_CO": 132705
 },
 {
   "TBL_ID": "DT_NSO_1001_021V1",
   "Period": 2019,
   "CODE": 34625,
   "SCR_MN": "Номгон",
   "SCR_ENG": "Nomgon",
   "CODE1": 1,
   "SCR_MN1": "Бүгд",
   "SCR_ENG1": "Total",
   "CODE2": "",
   "SCR_MN2": "",
   "SCR_ENG2": "",
   "DTVAL_CO": 302862
 },
 {
   "TBL_ID": "DT_NSO_1001_021V1",
   "Period": 2019,
   "CODE": 34628,
   "SCR_MN": "Сэврэй",
   "SCR_ENG": "Sevrei",
   "CODE1": 1,
   "SCR_MN1": "Бүгд",
   "SCR_ENG1": "Total",
   "CODE2": "",
   "SCR_MN2": "",
   "SCR_ENG2": "",
   "DTVAL_CO": 190480
 },
 {
   "TBL_ID": "DT_NSO_1001_021V1",
   "Period": 2019,
   "CODE": 34631,
   "SCR_MN": "Ханбогд",
   "SCR_ENG": "Khanbogd",
   "CODE1": 1,
   "SCR_MN1": "Бүгд",
   "SCR_ENG1": "Total",
   "CODE2": "",
   "SCR_MN2": "",
   "SCR_ENG2": "",
   "DTVAL_CO": 190028
 },
 {
   "TBL_ID": "DT_NSO_1001_021V1",
   "Period": 2019,
   "CODE": 34634,
   "SCR_MN": "Ханхонгор",
   "SCR_ENG": "Khankhongor",
   "CODE1": 1,
   "SCR_MN1": "Бүгд",
   "SCR_ENG1": "Total",
   "CODE2": "",
   "SCR_MN2": "",
   "SCR_ENG2": "",
   "DTVAL_CO": 280532
 },
 {
   "TBL_ID": "DT_NSO_1001_021V1",
   "Period": 2019,
   "CODE": 34637,
   "SCR_MN": "Хүрмэн",
   "SCR_ENG": "Khurmen",
   "CODE1": 1,
   "SCR_MN1": "Бүгд",
   "SCR_ENG1": "Total",
   "CODE2": "",
   "SCR_MN2": "",
   "SCR_ENG2": "",
   "DTVAL_CO": 169889
 },
 {
   "TBL_ID": "DT_NSO_1001_021V1",
   "Period": 2019,
   "CODE": 34640,
   "SCR_MN": "Цогт-Овоо",
   "SCR_ENG": "Tsogt-Ovoo",
   "CODE1": 1,
   "SCR_MN1": "Бүгд",
   "SCR_ENG1": "Total",
   "CODE2": "",
   "SCR_MN2": "",
   "SCR_ENG2": "",
   "DTVAL_CO": 154385
 },
 {
   "TBL_ID": "DT_NSO_1001_021V1",
   "Period": 2019,
   "CODE": 34643,
   "SCR_MN": "Цогтцэций",
   "SCR_ENG": "Tsogttsetsii",
   "CODE1": 1,
   "SCR_MN1": "Бүгд",
   "SCR_ENG1": "Total",
   "CODE2": "",
   "SCR_MN2": "",
   "SCR_ENG2": "",
   "DTVAL_CO": 159455
 },
 {
   "TBL_ID": "DT_NSO_1001_021V1",
   "Period": 2019,
   "CODE": 34801,
   "SCR_MN": "Сайнцагаан",
   "SCR_ENG": "Saintsagaan",
   "CODE1": 1,
   "SCR_MN1": "Бүгд",
   "SCR_ENG1": "Total",
   "CODE2": "",
   "SCR_MN2": "",
   "SCR_ENG2": "",
   "DTVAL_CO": 417543
 },
 {
   "TBL_ID": "DT_NSO_1001_021V1",
   "Period": 2019,
   "CODE": 34804,
   "SCR_MN": "Адаацаг",
   "SCR_ENG": "Adaatsag",
   "CODE1": 1,
   "SCR_MN1": "Бүгд",
   "SCR_ENG1": "Total",
   "CODE2": "",
   "SCR_MN2": "",
   "SCR_ENG2": "",
   "DTVAL_CO": 303502
 },
 {
   "TBL_ID": "DT_NSO_1001_021V1",
   "Period": 2019,
   "CODE": 34807,
   "SCR_MN": "Баянжаргалан",
   "SCR_ENG": "Bayanjargalan",
   "CODE1": 1,
   "SCR_MN1": "Бүгд",
   "SCR_ENG1": "Total",
   "CODE2": "",
   "SCR_MN2": "",
   "SCR_ENG2": "",
   "DTVAL_CO": 157326
 },
 {
   "TBL_ID": "DT_NSO_1001_021V1",
   "Period": 2019,
   "CODE": 34810,
   "SCR_MN": "Говь-Угтаал",
   "SCR_ENG": "Govi-Ugtaal",
   "CODE1": 1,
   "SCR_MN1": "Бүгд",
   "SCR_ENG1": "Total",
   "CODE2": "",
   "SCR_MN2": "",
   "SCR_ENG2": "",
   "DTVAL_CO": 207951
 },
 {
   "TBL_ID": "DT_NSO_1001_021V1",
   "Period": 2019,
   "CODE": 34813,
   "SCR_MN": "Гурвансайхан",
   "SCR_ENG": "Gurvansaikhan",
   "CODE1": 1,
   "SCR_MN1": "Бүгд",
   "SCR_ENG1": "Total",
   "CODE2": "",
   "SCR_MN2": "",
   "SCR_ENG2": "",
   "DTVAL_CO": 313218
 },
 {
   "TBL_ID": "DT_NSO_1001_021V1",
   "Period": 2019,
   "CODE": 34816,
   "SCR_MN": "Дэлгэрхангай",
   "SCR_ENG": "Delgerkhangai",
   "CODE1": 1,
   "SCR_MN1": "Бүгд",
   "SCR_ENG1": "Total",
   "CODE2": "",
   "SCR_MN2": "",
   "SCR_ENG2": "",
   "DTVAL_CO": 220387
 },
 {
   "TBL_ID": "DT_NSO_1001_021V1",
   "Period": 2019,
   "CODE": 34819,
   "SCR_MN": "Дэлгэрцогт",
   "SCR_ENG": "Delgertsogt",
   "CODE1": 1,
   "SCR_MN1": "Бүгд",
   "SCR_ENG1": "Total",
   "CODE2": "",
   "SCR_MN2": "",
   "SCR_ENG2": "",
   "DTVAL_CO": 199548
 },
 {
   "TBL_ID": "DT_NSO_1001_021V1",
   "Period": 2019,
   "CODE": 34822,
   "SCR_MN": "Дэрэн",
   "SCR_ENG": "Deren",
   "CODE1": 1,
   "SCR_MN1": "Бүгд",
   "SCR_ENG1": "Total",
   "CODE2": "",
   "SCR_MN2": "",
   "SCR_ENG2": "",
   "DTVAL_CO": 279008
 },
 {
   "TBL_ID": "DT_NSO_1001_021V1",
   "Period": 2019,
   "CODE": 34825,
   "SCR_MN": "Луус",
   "SCR_ENG": "Luus",
   "CODE1": 1,
   "SCR_MN1": "Бүгд",
   "SCR_ENG1": "Total",
   "CODE2": "",
   "SCR_MN2": "",
   "SCR_ENG2": "",
   "DTVAL_CO": 193936
 },
 {
   "TBL_ID": "DT_NSO_1001_021V1",
   "Period": 2019,
   "CODE": 34828,
   "SCR_MN": "Өлзийт",
   "SCR_ENG": "Ulziit",
   "CODE1": 1,
   "SCR_MN1": "Бүгд",
   "SCR_ENG1": "Total",
   "CODE2": "",
   "SCR_MN2": "",
   "SCR_ENG2": "",
   "DTVAL_CO": 369757
 },
 {
   "TBL_ID": "DT_NSO_1001_021V1",
   "Period": 2019,
   "CODE": 34831,
   "SCR_MN": "Өндөршил",
   "SCR_ENG": "Undurshil",
   "CODE1": 1,
   "SCR_MN1": "Бүгд",
   "SCR_ENG1": "Total",
   "CODE2": "",
   "SCR_MN2": "",
   "SCR_ENG2": "",
   "DTVAL_CO": 189659
 },
 {
   "TBL_ID": "DT_NSO_1001_021V1",
   "Period": 2019,
   "CODE": 34834,
   "SCR_MN": "Сайхан-Овоо",
   "SCR_ENG": "Saikhan-Ovoo",
   "CODE1": 1,
   "SCR_MN1": "Бүгд",
   "SCR_ENG1": "Total",
   "CODE2": "",
   "SCR_MN2": "",
   "SCR_ENG2": "",
   "DTVAL_CO": 207015
 },
 {
   "TBL_ID": "DT_NSO_1001_021V1",
   "Period": 2019,
   "CODE": 34837,
   "SCR_MN": "Хулд",
   "SCR_ENG": "Khuld",
   "CODE1": 1,
   "SCR_MN1": "Бүгд",
   "SCR_ENG1": "Total",
   "CODE2": "",
   "SCR_MN2": "",
   "SCR_ENG2": "",
   "DTVAL_CO": 295762
 },
 {
   "TBL_ID": "DT_NSO_1001_021V1",
   "Period": 2019,
   "CODE": 34840,
   "SCR_MN": "Цагаандэлгэр",
   "SCR_ENG": "Tsagaandelger",
   "CODE1": 1,
   "SCR_MN1": "Бүгд",
   "SCR_ENG1": "Total",
   "CODE2": "",
   "SCR_MN2": "",
   "SCR_ENG2": "",
   "DTVAL_CO": 152396
 },
 {
   "TBL_ID": "DT_NSO_1001_021V1",
   "Period": 2019,
   "CODE": 34843,
   "SCR_MN": "Эрдэнэдалай",
   "SCR_ENG": "Erdenedalai",
   "CODE1": 1,
   "SCR_MN1": "Бүгд",
   "SCR_ENG1": "Total",
   "CODE2": "",
   "SCR_MN2": "",
   "SCR_ENG2": "",
   "DTVAL_CO": 586113
 },
 {
   "TBL_ID": "DT_NSO_1001_021V1",
   "Period": 2019,
   "CODE": 42101,
   "SCR_MN": "Хэрлэн",
   "SCR_ENG": "Kherlen",
   "CODE1": 1,
   "SCR_MN1": "Бүгд",
   "SCR_ENG1": "Total",
   "CODE2": "",
   "SCR_MN2": "",
   "SCR_ENG2": "",
   "DTVAL_CO": 176047
 },
 {
   "TBL_ID": "DT_NSO_1001_021V1",
   "Period": 2019,
   "CODE": 42104,
   "SCR_MN": "Баяндун",
   "SCR_ENG": "Bayandun",
   "CODE1": 1,
   "SCR_MN1": "Бүгд",
   "SCR_ENG1": "Total",
   "CODE2": "",
   "SCR_MN2": "",
   "SCR_ENG2": "",
   "DTVAL_CO": 220678
 },
 {
   "TBL_ID": "DT_NSO_1001_021V1",
   "Period": 2019,
   "CODE": 42107,
   "SCR_MN": "Баянтүмэн",
   "SCR_ENG": "Bayantumen",
   "CODE1": 1,
   "SCR_MN1": "Бүгд",
   "SCR_ENG1": "Total",
   "CODE2": "",
   "SCR_MN2": "",
   "SCR_ENG2": "",
   "DTVAL_CO": 205636
 },
 {
   "TBL_ID": "DT_NSO_1001_021V1",
   "Period": 2019,
   "CODE": 42110,
   "SCR_MN": "Баян-Уул",
   "SCR_ENG": "Bayan-Uul",
   "CODE1": 1,
   "SCR_MN1": "Бүгд",
   "SCR_ENG1": "Total",
   "CODE2": "",
   "SCR_MN2": "",
   "SCR_ENG2": "",
   "DTVAL_CO": 133766
 },
 {
   "TBL_ID": "DT_NSO_1001_021V1",
   "Period": 2019,
   "CODE": 42113,
   "SCR_MN": "Булган",
   "SCR_ENG": "Bulgan",
   "CODE1": 1,
   "SCR_MN1": "Бүгд",
   "SCR_ENG1": "Total",
   "CODE2": "",
   "SCR_MN2": "",
   "SCR_ENG2": "",
   "DTVAL_CO": 208726
 },
 {
   "TBL_ID": "DT_NSO_1001_021V1",
   "Period": 2019,
   "CODE": 42116,
   "SCR_MN": "Гурванзагал",
   "SCR_ENG": "Gurvanzagal",
   "CODE1": 1,
   "SCR_MN1": "Бүгд",
   "SCR_ENG1": "Total",
   "CODE2": "",
   "SCR_MN2": "",
   "SCR_ENG2": "",
   "DTVAL_CO": 175187
 },
 {
   "TBL_ID": "DT_NSO_1001_021V1",
   "Period": 2019,
   "CODE": 42119,
   "SCR_MN": "Дашбалбар",
   "SCR_ENG": "Dashbalbar",
   "CODE1": 1,
   "SCR_MN1": "Бүгд",
   "SCR_ENG1": "Total",
   "CODE2": "",
   "SCR_MN2": "",
   "SCR_ENG2": "",
   "DTVAL_CO": 311110
 },
 {
   "TBL_ID": "DT_NSO_1001_021V1",
   "Period": 2019,
   "CODE": 42122,
   "SCR_MN": "Матад",
   "SCR_ENG": "Matad",
   "CODE1": 1,
   "SCR_MN1": "Бүгд",
   "SCR_ENG1": "Total",
   "CODE2": "",
   "SCR_MN2": "",
   "SCR_ENG2": "",
   "DTVAL_CO": 184529
 },
 {
   "TBL_ID": "DT_NSO_1001_021V1",
   "Period": 2019,
   "CODE": 42125,
   "SCR_MN": "Сэргэлэн",
   "SCR_ENG": "Sergelen",
   "CODE1": 1,
   "SCR_MN1": "Бүгд",
   "SCR_ENG1": "Total",
   "CODE2": "",
   "SCR_MN2": "",
   "SCR_ENG2": "",
   "DTVAL_CO": 225546
 },
 {
   "TBL_ID": "DT_NSO_1001_021V1",
   "Period": 2019,
   "CODE": 42128,
   "SCR_MN": "Халхгол",
   "SCR_ENG": "Khalkhgol",
   "CODE1": 1,
   "SCR_MN1": "Бүгд",
   "SCR_ENG1": "Total",
   "CODE2": "",
   "SCR_MN2": "",
   "SCR_ENG2": "",
   "DTVAL_CO": 91993
 },
 {
   "TBL_ID": "DT_NSO_1001_021V1",
   "Period": 2019,
   "CODE": 42131,
   "SCR_MN": "Хөлөнбуйр",
   "SCR_ENG": "Khulunbuir",
   "CODE1": 1,
   "SCR_MN1": "Бүгд",
   "SCR_ENG1": "Total",
   "CODE2": "",
   "SCR_MN2": "",
   "SCR_ENG2": "",
   "DTVAL_CO": 161451
 },
 {
   "TBL_ID": "DT_NSO_1001_021V1",
   "Period": 2019,
   "CODE": 42134,
   "SCR_MN": "Цагаан-Овоо",
   "SCR_ENG": "Tsagaan-Ovoo",
   "CODE1": 1,
   "SCR_MN1": "Бүгд",
   "SCR_ENG1": "Total",
   "CODE2": "",
   "SCR_MN2": "",
   "SCR_ENG2": "",
   "DTVAL_CO": 242850
 },
 {
   "TBL_ID": "DT_NSO_1001_021V1",
   "Period": 2019,
   "CODE": 42137,
   "SCR_MN": "Чойбалсан",
   "SCR_ENG": "Choibalsan",
   "CODE1": 1,
   "SCR_MN1": "Бүгд",
   "SCR_ENG1": "Total",
   "CODE2": "",
   "SCR_MN2": "",
   "SCR_ENG2": "",
   "DTVAL_CO": 179852
 },
 {
   "TBL_ID": "DT_NSO_1001_021V1",
   "Period": 2019,
   "CODE": 42140,
   "SCR_MN": "Чулуунхороот",
   "SCR_ENG": "Chuluunkhoroot",
   "CODE1": 1,
   "SCR_MN1": "Бүгд",
   "SCR_ENG1": "Total",
   "CODE2": "",
   "SCR_MN2": "",
   "SCR_ENG2": "",
   "DTVAL_CO": 112251
 },
 {
   "TBL_ID": "DT_NSO_1001_021V1",
   "Period": 2019,
   "CODE": 42201,
   "SCR_MN": "Баруун-Урт",
   "SCR_ENG": "Baruun-Urt",
   "CODE1": 1,
   "SCR_MN1": "Бүгд",
   "SCR_ENG1": "Total",
   "CODE2": "",
   "SCR_MN2": "",
   "SCR_ENG2": "",
   "DTVAL_CO": 399702
 },
 {
   "TBL_ID": "DT_NSO_1001_021V1",
   "Period": 2019,
   "CODE": 42204,
   "SCR_MN": "Асгат",
   "SCR_ENG": "Asgat",
   "CODE1": 1,
   "SCR_MN1": "Бүгд",
   "SCR_ENG1": "Total",
   "CODE2": "",
   "SCR_MN2": "",
   "SCR_ENG2": "",
   "DTVAL_CO": 176252
 },
 {
   "TBL_ID": "DT_NSO_1001_021V1",
   "Period": 2019,
   "CODE": 42207,
   "SCR_MN": "Баяндэлгэр",
   "SCR_ENG": "Bayandelger",
   "CODE1": 1,
   "SCR_MN1": "Бүгд",
   "SCR_ENG1": "Total",
   "CODE2": "",
   "SCR_MN2": "",
   "SCR_ENG2": "",
   "DTVAL_CO": 508091
 },
 {
   "TBL_ID": "DT_NSO_1001_021V1",
   "Period": 2019,
   "CODE": 42210,
   "SCR_MN": "Дарьганга",
   "SCR_ENG": "Dariganga",
   "CODE1": 1,
   "SCR_MN1": "Бүгд",
   "SCR_ENG1": "Total",
   "CODE2": "",
   "SCR_MN2": "",
   "SCR_ENG2": "",
   "DTVAL_CO": 226717
 },
 {
   "TBL_ID": "DT_NSO_1001_021V1",
   "Period": 2019,
   "CODE": 42213,
   "SCR_MN": "Мөнххаан",
   "SCR_ENG": "Munkhkhaan",
   "CODE1": 1,
   "SCR_MN1": "Бүгд",
   "SCR_ENG1": "Total",
   "CODE2": "",
   "SCR_MN2": "",
   "SCR_ENG2": "",
   "DTVAL_CO": 427481
 },
 {
   "TBL_ID": "DT_NSO_1001_021V1",
   "Period": 2019,
   "CODE": 42216,
   "SCR_MN": "Наран",
   "SCR_ENG": "Naran",
   "CODE1": 1,
   "SCR_MN1": "Бүгд",
   "SCR_ENG1": "Total",
   "CODE2": "",
   "SCR_MN2": "",
   "SCR_ENG2": "",
   "DTVAL_CO": 135798
 },
 {
   "TBL_ID": "DT_NSO_1001_021V1",
   "Period": 2019,
   "CODE": 42219,
   "SCR_MN": "Онгон",
   "SCR_ENG": "Ongon",
   "CODE1": 1,
   "SCR_MN1": "Бүгд",
   "SCR_ENG1": "Total",
   "CODE2": "",
   "SCR_MN2": "",
   "SCR_ENG2": "",
   "DTVAL_CO": 331647
 },
 {
   "TBL_ID": "DT_NSO_1001_021V1",
   "Period": 2019,
   "CODE": 42222,
   "SCR_MN": "Сүхбаатар",
   "SCR_ENG": "Sukhbaatar",
   "CODE1": 1,
   "SCR_MN1": "Бүгд",
   "SCR_ENG1": "Total",
   "CODE2": "",
   "SCR_MN2": "",
   "SCR_ENG2": "",
   "DTVAL_CO": 359718
 },
 {
   "TBL_ID": "DT_NSO_1001_021V1",
   "Period": 2019,
   "CODE": 42225,
   "SCR_MN": "Түвшинширээ",
   "SCR_ENG": "Tuvshinshiree",
   "CODE1": 1,
   "SCR_MN1": "Бүгд",
   "SCR_ENG1": "Total",
   "CODE2": "",
   "SCR_MN2": "",
   "SCR_ENG2": "",
   "DTVAL_CO": 321988
 },
 {
   "TBL_ID": "DT_NSO_1001_021V1",
   "Period": 2019,
   "CODE": 42228,
   "SCR_MN": "Түмэнцогт",
   "SCR_ENG": "Tumentsogt",
   "CODE1": 1,
   "SCR_MN1": "Бүгд",
   "SCR_ENG1": "Total",
   "CODE2": "",
   "SCR_MN2": "",
   "SCR_ENG2": "",
   "DTVAL_CO": 140482
 },
 {
   "TBL_ID": "DT_NSO_1001_021V1",
   "Period": 2019,
   "CODE": 42231,
   "SCR_MN": "Уулбаян",
   "SCR_ENG": "Uulbayan",
   "CODE1": 1,
   "SCR_MN1": "Бүгд",
   "SCR_ENG1": "Total",
   "CODE2": "",
   "SCR_MN2": "",
   "SCR_ENG2": "",
   "DTVAL_CO": 245470
 },
 {
   "TBL_ID": "DT_NSO_1001_021V1",
   "Period": 2019,
   "CODE": 42234,
   "SCR_MN": "Халзан",
   "SCR_ENG": "Khalzan",
   "CODE1": 1,
   "SCR_MN1": "Бүгд",
   "SCR_ENG1": "Total",
   "CODE2": "",
   "SCR_MN2": "",
   "SCR_ENG2": "",
   "DTVAL_CO": 162690
 },
 {
   "TBL_ID": "DT_NSO_1001_021V1",
   "Period": 2019,
   "CODE": 42237,
   "SCR_MN": "Эрдэнэцагаан",
   "SCR_ENG": "Erdenetsagaan",
   "CODE1": 1,
   "SCR_MN1": "Бүгд",
   "SCR_ENG1": "Total",
   "CODE2": "",
   "SCR_MN2": "",
   "SCR_ENG2": "",
   "DTVAL_CO": 380974
 },
 {
   "TBL_ID": "DT_NSO_1001_021V1",
   "Period": 2019,
   "CODE": 42301,
   "SCR_MN": "Хэрлэн",
   "SCR_ENG": "Kherlen",
   "CODE1": 1,
   "SCR_MN1": "Бүгд",
   "SCR_ENG1": "Total",
   "CODE2": "",
   "SCR_MN2": "",
   "SCR_ENG2": "",
   "DTVAL_CO": 520416
 },
 {
   "TBL_ID": "DT_NSO_1001_021V1",
   "Period": 2019,
   "CODE": 42304,
   "SCR_MN": "Батноров",
   "SCR_ENG": "Batnorov",
   "CODE1": 1,
   "SCR_MN1": "Бүгд",
   "SCR_ENG1": "Total",
   "CODE2": "",
   "SCR_MN2": "",
   "SCR_ENG2": "",
   "DTVAL_CO": 456158
 },
 {
   "TBL_ID": "DT_NSO_1001_021V1",
   "Period": 2019,
   "CODE": 42307,
   "SCR_MN": "Батширээт",
   "SCR_ENG": "Batshireet",
   "CODE1": 1,
   "SCR_MN1": "Бүгд",
   "SCR_ENG1": "Total",
   "CODE2": "",
   "SCR_MN2": "",
   "SCR_ENG2": "",
   "DTVAL_CO": 81400
 },
 {
   "TBL_ID": "DT_NSO_1001_021V1",
   "Period": 2019,
   "CODE": 42310,
   "SCR_MN": "Баян-Адарга",
   "SCR_ENG": "Bayan-Adarga",
   "CODE1": 1,
   "SCR_MN1": "Бүгд",
   "SCR_ENG1": "Total",
   "CODE2": "",
   "SCR_MN2": "",
   "SCR_ENG2": "",
   "DTVAL_CO": 195178
 },
 {
   "TBL_ID": "DT_NSO_1001_021V1",
   "Period": 2019,
   "CODE": 42313,
   "SCR_MN": "Баянмөнх",
   "SCR_ENG": "Bayanmunkh",
   "CODE1": 1,
   "SCR_MN1": "Бүгд",
   "SCR_ENG1": "Total",
   "CODE2": "",
   "SCR_MN2": "",
   "SCR_ENG2": "",
   "DTVAL_CO": 192271
 },
 {
   "TBL_ID": "DT_NSO_1001_021V1",
   "Period": 2019,
   "CODE": 42316,
   "SCR_MN": "Баян-Овоо",
   "SCR_ENG": "Bayan-Ovoo",
   "CODE1": 1,
   "SCR_MN1": "Бүгд",
   "SCR_ENG1": "Total",
   "CODE2": "",
   "SCR_MN2": "",
   "SCR_ENG2": "",
   "DTVAL_CO": 208973
 },
 {
   "TBL_ID": "DT_NSO_1001_021V1",
   "Period": 2019,
   "CODE": 42319,
   "SCR_MN": "Баянхутаг",
   "SCR_ENG": "Bayankhutag",
   "CODE1": 1,
   "SCR_MN1": "Бүгд",
   "SCR_ENG1": "Total",
   "CODE2": "",
   "SCR_MN2": "",
   "SCR_ENG2": "",
   "DTVAL_CO": 460350
 },
 {
   "TBL_ID": "DT_NSO_1001_021V1",
   "Period": 2019,
   "CODE": 42322,
   "SCR_MN": "Биндэр",
   "SCR_ENG": "Binder",
   "CODE1": 1,
   "SCR_MN1": "Бүгд",
   "SCR_ENG1": "Total",
   "CODE2": "",
   "SCR_MN2": "",
   "SCR_ENG2": "",
   "DTVAL_CO": 266861
 },
 {
   "TBL_ID": "DT_NSO_1001_021V1",
   "Period": 2019,
   "CODE": 42325,
   "SCR_MN": "Галшар",
   "SCR_ENG": "Galshar",
   "CODE1": 1,
   "SCR_MN1": "Бүгд",
   "SCR_ENG1": "Total",
   "CODE2": "",
   "SCR_MN2": "",
   "SCR_ENG2": "",
   "DTVAL_CO": 324718
 },
 {
   "TBL_ID": "DT_NSO_1001_021V1",
   "Period": 2019,
   "CODE": 42328,
   "SCR_MN": "Дадал",
   "SCR_ENG": "Dadal",
   "CODE1": 1,
   "SCR_MN1": "Бүгд",
   "SCR_ENG1": "Total",
   "CODE2": "",
   "SCR_MN2": "",
   "SCR_ENG2": "",
   "DTVAL_CO": 55169
 },
 {
   "TBL_ID": "DT_NSO_1001_021V1",
   "Period": 2019,
   "CODE": 42331,
   "SCR_MN": "Дархан",
   "SCR_ENG": "Darkhan",
   "CODE1": 1,
   "SCR_MN1": "Бүгд",
   "SCR_ENG1": "Total",
   "CODE2": "",
   "SCR_MN2": "",
   "SCR_ENG2": "",
   "DTVAL_CO": 256287
 },
 {
   "TBL_ID": "DT_NSO_1001_021V1",
   "Period": 2019,
   "CODE": 42334,
   "SCR_MN": "Дэлгэрхаан",
   "SCR_ENG": "Delgerkhaan",
   "CODE1": 1,
   "SCR_MN1": "Бүгд",
   "SCR_ENG1": "Total",
   "CODE2": "",
   "SCR_MN2": "",
   "SCR_ENG2": "",
   "DTVAL_CO": 274257
 },
 {
   "TBL_ID": "DT_NSO_1001_021V1",
   "Period": 2019,
   "CODE": 42337,
   "SCR_MN": "Жаргалтхаан",
   "SCR_ENG": "Jargaltkhaan",
   "CODE1": 1,
   "SCR_MN1": "Бүгд",
   "SCR_ENG1": "Total",
   "CODE2": "",
   "SCR_MN2": "",
   "SCR_ENG2": "",
   "DTVAL_CO": 226202
 },
 {
   "TBL_ID": "DT_NSO_1001_021V1",
   "Period": 2019,
   "CODE": 42340,
   "SCR_MN": "Мөрөн",
   "SCR_ENG": "Murun",
   "CODE1": 1,
   "SCR_MN1": "Бүгд",
   "SCR_ENG1": "Total",
   "CODE2": "",
   "SCR_MN2": "",
   "SCR_ENG2": "",
   "DTVAL_CO": 192519
 },
 {
   "TBL_ID": "DT_NSO_1001_021V1",
   "Period": 2019,
   "CODE": 42343,
   "SCR_MN": "Норовлин",
   "SCR_ENG": "Norovlin",
   "CODE1": 1,
   "SCR_MN1": "Бүгд",
   "SCR_ENG1": "Total",
   "CODE2": "",
   "SCR_MN2": "",
   "SCR_ENG2": "",
   "DTVAL_CO": 180737
 },
 {
   "TBL_ID": "DT_NSO_1001_021V1",
   "Period": 2019,
   "CODE": 42346,
   "SCR_MN": "Өмнөдэлгэр",
   "SCR_ENG": "Umnudelger",
   "CODE1": 1,
   "SCR_MN1": "Бүгд",
   "SCR_ENG1": "Total",
   "CODE2": "",
   "SCR_MN2": "",
   "SCR_ENG2": "",
   "DTVAL_CO": 639902
 },
 {
   "TBL_ID": "DT_NSO_1001_021V1",
   "Period": 2019,
   "CODE": 42349,
   "SCR_MN": "Цэнхэрмандал",
   "SCR_ENG": "Tsenkhermandal",
   "CODE1": 1,
   "SCR_MN1": "Бүгд",
   "SCR_ENG1": "Total",
   "CODE2": "",
   "SCR_MN2": "",
   "SCR_ENG2": "",
   "DTVAL_CO": 253518
 },
 {
   "TBL_ID": "DT_NSO_1001_021V1",
   "Period": 2019,
   "CODE": 42352,
   "SCR_MN": "Бор-Өндөр",
   "SCR_ENG": "Bor-Undur",
   "CODE1": 1,
   "SCR_MN1": "Бүгд",
   "SCR_ENG1": "Total",
   "CODE2": "",
   "SCR_MN2": "",
   "SCR_ENG2": "",
   "DTVAL_CO": 83445
 },
 {
   "TBL_ID": "DT_NSO_1001_021V1",
   "Period": 2019,
   "CODE": 51101,
   "SCR_MN": "Багануур",
   "SCR_ENG": "Baganuur",
   "CODE1": 1,
   "SCR_MN1": "Бүгд",
   "SCR_ENG1": "Total",
   "CODE2": "",
   "SCR_MN2": "",
   "SCR_ENG2": "",
   "DTVAL_CO": 200183
 },
 {
   "TBL_ID": "DT_NSO_1001_021V1",
   "Period": 2019,
   "CODE": 51104,
   "SCR_MN": "Багахангай",
   "SCR_ENG": "Bagakhangai",
   "CODE1": 1,
   "SCR_MN1": "Бүгд",
   "SCR_ENG1": "Total",
   "CODE2": "",
   "SCR_MN2": "",
   "SCR_ENG2": "",
   "DTVAL_CO": 21293
 },
 {
   "TBL_ID": "DT_NSO_1001_021V1",
   "Period": 2019,
   "CODE": 51107,
   "SCR_MN": "Баянгол",
   "SCR_ENG": "Bayangol",
   "CODE1": 1,
   "SCR_MN1": "Бүгд",
   "SCR_ENG1": "Total",
   "CODE2": "",
   "SCR_MN2": "",
   "SCR_ENG2": "",
   "DTVAL_CO": 0
 },
 {
   "TBL_ID": "DT_NSO_1001_021V1",
   "Period": 2019,
   "CODE": 51110,
   "SCR_MN": "Баянзүрх",
   "SCR_ENG": "Bayanzurkh",
   "CODE1": 1,
   "SCR_MN1": "Бүгд",
   "SCR_ENG1": "Total",
   "CODE2": "",
   "SCR_MN2": "",
   "SCR_ENG2": "",
   "DTVAL_CO": 56933
 },
 {
   "TBL_ID": "DT_NSO_1001_021V1",
   "Period": 2019,
   "CODE": 51113,
   "SCR_MN": "Налайх",
   "SCR_ENG": "Nalaikh",
   "CODE1": 1,
   "SCR_MN1": "Бүгд",
   "SCR_ENG1": "Total",
   "CODE2": "",
   "SCR_MN2": "",
   "SCR_ENG2": "",
   "DTVAL_CO": 57075
 },
 {
   "TBL_ID": "DT_NSO_1001_021V1",
   "Period": 2019,
   "CODE": 51116,
   "SCR_MN": "Сонгинохайрхан",
   "SCR_ENG": "Songinokhairkhan",
   "CODE1": 1,
   "SCR_MN1": "Бүгд",
   "SCR_ENG1": "Total",
   "CODE2": "",
   "SCR_MN2": "",
   "SCR_ENG2": "",
   "DTVAL_CO": 70768
 },
 {
   "TBL_ID": "DT_NSO_1001_021V1",
   "Period": 2019,
   "CODE": 51119,
   "SCR_MN": "Сүхбаатар",
   "SCR_ENG": "Sukhbaatar",
   "CODE1": 1,
   "SCR_MN1": "Бүгд",
   "SCR_ENG1": "Total",
   "CODE2": "",
   "SCR_MN2": "",
   "SCR_ENG2": "",
   "DTVAL_CO": 0
 },
 {
   "TBL_ID": "DT_NSO_1001_021V1",
   "Period": 2019,
   "CODE": 51122,
   "SCR_MN": "Хан-Уул",
   "SCR_ENG": "Khan-Uul",
   "CODE1": 1,
   "SCR_MN1": "Бүгд",
   "SCR_ENG1": "Total",
   "CODE2": "",
   "SCR_MN2": "",
   "SCR_ENG2": "",
   "DTVAL_CO": 38639
 },
 {
   "TBL_ID": "DT_NSO_1001_021V1",
   "Period": 2019,
   "CODE": 51125,
   "SCR_MN": "Чингэлтэй",
   "SCR_ENG": "Chingeltei",
   "CODE1": 1,
   "SCR_MN1": "Бүгд",
   "SCR_ENG1": "Total",
   "CODE2": "",
   "SCR_MN2": "",
   "SCR_ENG2": "",
   "DTVAL_CO": 0
 },
 {
   "TBL_ID": "DT_NSO_1001_021V1",
   "Period": 2019,
   "CODE": 18407,
   "SCR_MN": "Булган",
   "SCR_ENG": "Bulgan",
   "CODE1": 1,
   "SCR_MN1": "Бүгд",
   "SCR_ENG1": "Total",
   "CODE2": "",
   "SCR_MN2": "",
   "SCR_ENG2": "",
   "DTVAL_CO": 314653
}
],
"Response": "success"
}