[{"sindex":224,"date":"2020-5-01","lat":48.74804,"lon":96.0043,"sum_rrr":0.0},{"sindex":225,"date":"2020-5-01","lat":48.76211,"lon":98.2654,"sum_rrr":1.5},{"sindex":232,"date":"2020-5-01","lat":49.39368,"lon":102.7091,"sum_rrr":0.5},{"sindex":233,"date":"2020-5-01","lat":49.45553,"lon":103.9776,"sum_rrr":3.8},{"sindex":246,"date":"2020-5-01","lat":48.22759,"lon":106.2854,"sum_rrr":4.7},{"sindex":274,"date":"2020-5-01","lat":47.20964,"lon":97.6047,"sum_rrr":0.0},{"sindex":277,"date":"2020-5-01","lat":46.37616,"lon":96.2387,"sum_rrr":6.6},{"sindex":297,"date":"2020-5-01","lat":47.86707,"lon":105.2507,"sum_rrr":0.3},{"sindex":503,"date":"2020-5-01","lat":48.72473,"lon":100.7667,"sum_rrr":4.9},{"sindex":623,"date":"2020-5-01","lat":43.87498,"lon":110.4256,"sum_rrr":0.0},{"sindex":636,"date":"2020-5-01","lat":49.24637,"lon":113.3698,"sum_rrr":5.0},{"sindex":692,"date":"2020-5-01","lat":48.12792,"lon":95.7126,"sum_rrr":0.0},{"sindex":801,"date":"2020-5-01","lat":48.48755,"lon":106.262,"sum_rrr":7.1},{"sindex":241,"date":"2020-5-01","lat":48.91319,"lon":106.0896,"sum_rrr":11.4},{"sindex":253,"date":"2020-5-01","lat":48.86049,"lon":106.4431,"sum_rrr":5.9},{"sindex":255,"date":"2020-5-01","lat":49.11418,"lon":112.6581,"sum_rrr":8.1},{"sindex":299,"date":"2020-5-01","lat":46.63178,"lon":109.4094,"sum_rrr":0.4},{"sindex":386,"date":"2020-5-01","lat":43.60447,"lon":109.6362,"sum_rrr":1.4},{"sindex":656,"date":"2020-5-01","lat":46.39198,"lon":105.7298,"sum_rrr":0.0},{"sindex":906,"date":"2020-5-01","lat":47.94708,"lon":111.5041,"sum_rrr":26.3},{"sindex":908,"date":"2020-5-01","lat":48.5515,"lon":111.0718,"sum_rrr":6.6},{"sindex":296,"date":"2020-5-01","lat":47.80651,"lon":108.3389,"sum_rrr":2.1},{"sindex":204,"date":"2020-5-01","lat":49.28182,"lon":90.9118,"sum_rrr":2.4},{"sindex":832,"date":"2020-5-01","lat":49.04197,"lon":92.0712,"sum_rrr":0.0},{"sindex":217,"date":"2020-5-01","lat":48.29928,"lon":89.51491,"sum_rrr":1.3},{"sindex":330,"date":"2020-5-01","lat":47.19446,"lon":102.8297,"sum_rrr":0.7},{"sindex":811,"date":"2020-5-01","lat":47.71384,"lon":107.7918,"sum_rrr":0.0},{"sindex":593,"date":"2020-5-01","lat":46.47057,"lon":94.1008,"sum_rrr":0.5},{"sindex":641,"date":"2020-5-01","lat":48.51008,"lon":114.0225,"sum_rrr":0.0},{"sindex":642,"date":"2020-5-01","lat":47.99013,"lon":118.1087,"sum_rrr":7.7},{"sindex":643,"date":"2020-5-01","lat":47.92366,"lon":112.9544,"sum_rrr":0.0},{"sindex":877,"date":"2020-5-01","lat":49.91417,"lon":99.45046,"sum_rrr":0.3},{"sindex":580,"date":"2020-5-01","lat":49.32087,"lon":104.3797,"sum_rrr":8.6},{"sindex":707,"date":"2020-5-01","lat":46.81336,"lon":102.2421,"sum_rrr":2.5},{"sindex":713,"date":"2020-5-01","lat":46.52594,"lon":102.5934,"sum_rrr":3.2},{"sindex":720,"date":"2020-5-01","lat":45.96165,"lon":102.0559,"sum_rrr":1.0},{"sindex":858,"date":"2020-5-01","lat":48.23786,"lon":91.9239,"sum_rrr":0.1},{"sindex":200,"date":"2020-5-01","lat":48.93934,"lon":91.16133,"sum_rrr":0.0},{"sindex":234,"date":"2020-5-01","lat":48.95005,"lon":99.53423,"sum_rrr":0.0},{"sindex":214,"date":"2020-5-01","lat":48.97962,"lon":89.93815,"sum_rrr":6.0},{"sindex":282,"date":"2020-5-01","lat":47.47117,"lon":101.4628,"sum_rrr":1.6},{"sindex":338,"date":"2020-5-01","lat":44.67415,"lon":102.1755,"sum_rrr":7.9},{"sindex":514,"date":"2020-5-01","lat":48.88559,"lon":101.2373,"sum_rrr":0.9},{"sindex":550,"date":"2020-5-01","lat":44.8002,"lon":98.65219,"sum_rrr":0.0},{"sindex":574,"date":"2020-5-01","lat":47.8473,"lon":104.0436,"sum_rrr":0.4},{"sindex":582,"date":"2020-5-01","lat":47.83125,"lon":104.4487,"sum_rrr":0.1},{"sindex":638,"date":"2020-5-01","lat":48.44192,"lon":114.8803,"sum_rrr":0.0},{"sindex":677,"date":"2020-5-01","lat":49.30407,"lon":96.3438,"sum_rrr":0.6},{"sindex":690,"date":"2020-5-01","lat":47.11527,"lon":96.6638,"sum_rrr":1.2},{"sindex":757,"date":"2020-5-01","lat":46.22841,"lon":111.8055,"sum_rrr":6.7},{"sindex":793,"date":"2020-5-01","lat":48.44981,"lon":105.3194,"sum_rrr":5.9},{"sindex":807,"date":"2020-5-01","lat":47.44888,"lon":105.055,"sum_rrr":0.0},{"sindex":834,"date":"2020-5-01","lat":50.33781,"lon":91.6153,"sum_rrr":0.9},{"sindex":840,"date":"2020-5-01","lat":49.39826,"lon":94.2498,"sum_rrr":1.0},{"sindex":853,"date":"2020-5-01","lat":46.93732,"lon":93.6123,"sum_rrr":6.4},{"sindex":888,"date":"2020-5-01","lat":51.49564,"lon":100.6707,"sum_rrr":1.5},{"sindex":252,"date":"2020-5-01","lat":48.54543,"lon":105.882,"sum_rrr":11.9},{"sindex":501,"date":"2020-5-01","lat":47.79331,"lon":101.9625,"sum_rrr":0.0},{"sindex":506,"date":"2020-5-01","lat":48.10273,"lon":102.5542,"sum_rrr":0.3},{"sindex":517,"date":"2020-5-01","lat":48.10575,"lon":99.1352,"sum_rrr":0.0},{"sindex":805,"date":"2020-5-01","lat":48.23617,"lon":104.7697,"sum_rrr":1.7},{"sindex":533,"date":"2020-5-01","lat":48.9442,"lon":89.14675,"sum_rrr":0.6},{"sindex":571,"date":"2020-5-01","lat":49.04133,"lon":102.0914,"sum_rrr":0.5},{"sindex":576,"date":"2020-5-01","lat":48.62484,"lon":103.5486,"sum_rrr":0.0},{"sindex":684,"date":"2020-5-01","lat":49.02011,"lon":95.9232,"sum_rrr":0.3},{"sindex":693,"date":"2020-5-01","lat":48.11277,"lon":96.7699,"sum_rrr":0.0},{"sindex":736,"date":"2020-5-01","lat":42.90253,"lon":105.2201,"sum_rrr":1.2},{"sindex":780,"date":"2020-5-01","lat":49.77446,"lon":107.5216,"sum_rrr":15.7},{"sindex":783,"date":"2020-5-01","lat":49.42072,"lon":107.2795,"sum_rrr":9.6},{"sindex":836,"date":"2020-5-01","lat":50.0971,"lon":91.6676,"sum_rrr":0.0},{"sindex":864,"date":"2020-5-01","lat":48.33619,"lon":92.6258,"sum_rrr":2.2},{"sindex":879,"date":"2020-5-01","lat":49.62128,"lon":99.58694,"sum_rrr":1.2},{"sindex":882,"date":"2020-5-01","lat":49.43915,"lon":101.4619,"sum_rrr":0.3},{"sindex":884,"date":"2020-5-01","lat":49.47979,"lon":100.9011,"sum_rrr":0.4},{"sindex":199,"date":"2020-5-01","lat":49.38372,"lon":92.5821,"sum_rrr":0.0},{"sindex":213,"date":"2020-5-01","lat":49.6585,"lon":94.4041,"sum_rrr":1.5},{"sindex":227,"date":"2020-5-01","lat":48.32226,"lon":95.1068,"sum_rrr":0.0},{"sindex":373,"date":"2020-5-01","lat":43.57722,"lon":104.4181,"sum_rrr":5.2},{"sindex":572,"date":"2020-5-01","lat":49.05929,"lon":103.6738,"sum_rrr":2.9},{"sindex":573,"date":"2020-5-01","lat":48.25189,"lon":103.868,"sum_rrr":1.0},{"sindex":531,"date":"2020-5-01","lat":48.41058,"lon":90.29956,"sum_rrr":1.0},{"sindex":559,"date":"2020-5-01","lat":46.4195,"lon":100.8308,"sum_rrr":7.8},{"sindex":203,"date":"2020-5-01","lat":51.11342,"lon":99.66757,"sum_rrr":1.3},{"sindex":691,"date":"2020-5-01","lat":46.79749,"lon":97.1915,"sum_rrr":0.0},{"sindex":711,"date":"2020-5-01","lat":45.463,"lon":102.4247,"sum_rrr":0.3},{"sindex":714,"date":"2020-5-01","lat":45.96086,"lon":101.4533,"sum_rrr":3.3},{"sindex":772,"date":"2020-5-01","lat":49.16889,"lon":104.8423,"sum_rrr":1.2},{"sindex":236,"date":"2020-5-01","lat":49.0371,"lon":104.0867,"sum_rrr":3.8},{"sindex":810,"date":"2020-5-01","lat":47.94693,"lon":105.8984,"sum_rrr":0.4},{"sindex":876,"date":"2020-5-01","lat":50.12018,"lon":100.0457,"sum_rrr":1.1},{"sindex":886,"date":"2020-5-01","lat":49.85793,"lon":100.6316,"sum_rrr":1.1},{"sindex":889,"date":"2020-5-01","lat":49.60327,"lon":98.6929,"sum_rrr":1.0},{"sindex":212,"date":"2020-5-01","lat":49.97145,"lon":92.0778,"sum_rrr":0.0},{"sindex":216,"date":"2020-5-01","lat":48.82399,"lon":93.0982,"sum_rrr":0.0},{"sindex":223,"date":"2020-5-01","lat":49.12101,"lon":101.4564,"sum_rrr":1.0},{"sindex":238,"date":"2020-5-01","lat":48.58003,"lon":99.34692,"sum_rrr":0.0},{"sindex":285,"date":"2020-5-01","lat":46.89958,"lon":102.7784,"sum_rrr":2.2},{"sindex":331,"date":"2020-5-01","lat":45.17833,"lon":101.4133,"sum_rrr":0.4},{"sindex":502,"date":"2020-5-01","lat":47.31935,"lon":101.1092,"sum_rrr":2.6},{"sindex":512,"date":"2020-5-01","lat":47.36365,"lon":102.4646,"sum_rrr":0.0},{"sindex":719,"date":"2020-5-01","lat":46.46255,"lon":102.2841,"sum_rrr":4.0},{"sindex":887,"date":"2020-5-01","lat":50.67791,"lon":99.2291,"sum_rrr":4.3},{"sindex":594,"date":"2020-5-01","lat":46.35315,"lon":97.3637,"sum_rrr":0.0},{"sindex":209,"date":"2020-5-01","lat":50.11059,"lon":105.4519,"sum_rrr":3.5},{"sindex":686,"date":"2020-5-01","lat":48.64182,"lon":97.6157,"sum_rrr":1.3},{"sindex":796,"date":"2020-5-01","lat":47.17857,"lon":108.2567,"sum_rrr":0.1},{"sindex":828,"date":"2020-5-01","lat":49.90896,"lon":93.7825,"sum_rrr":1.1},{"sindex":891,"date":"2020-5-01","lat":50.47631,"lon":100.9266,"sum_rrr":3.1},{"sindex":942,"date":"2020-5-01","lat":47.79641,"lon":106.7031,"sum_rrr":0.6},{"sindex":676,"date":"2020-5-01","lat":47.64446,"lon":96.5326,"sum_rrr":0.0},{"sindex":689,"date":"2020-5-01","lat":47.49468,"lon":96.8062,"sum_rrr":0.5},{"sindex":731,"date":"2020-5-01","lat":43.49046,"lon":103.5231,"sum_rrr":0.4},{"sindex":733,"date":"2020-5-01","lat":44.65636,"lon":104.0568,"sum_rrr":0.0},{"sindex":751,"date":"2020-5-01","lat":46.38524,"lon":113.5772,"sum_rrr":10.4},{"sindex":941,"date":"2020-5-01","lat":48.12589,"lon":106.627,"sum_rrr":1.4},{"sindex":191,"date":"2020-5-01","lat":49.26808,"lon":94.8589,"sum_rrr":0.0},{"sindex":205,"date":"2020-5-01","lat":49.93546,"lon":102.6671,"sum_rrr":2.2},{"sindex":263,"date":"2020-5-01","lat":46.92988,"lon":91.08156,"sum_rrr":0.4},{"sindex":529,"date":"2020-5-01","lat":48.581,"lon":89.54357,"sum_rrr":0.4},{"sindex":839,"date":"2020-5-01","lat":49.67518,"lon":93.7784,"sum_rrr":5.1},{"sindex":755,"date":"2020-5-01","lat":45.37353,"lon":113.1299,"sum_rrr":2.2},{"sindex":827,"date":"2020-5-01","lat":50.61769,"lon":92.399,"sum_rrr":0.4},{"sindex":261,"date":"2020-5-01","lat":47.8626,"lon":90.69704,"sum_rrr":1.9},{"sindex":262,"date":"2020-5-01","lat":47.35494,"lon":94.5223,"sum_rrr":1.0},{"sindex":382,"date":"2020-5-01","lat":44.13877,"lon":107.4489,"sum_rrr":0.4},{"sindex":505,"date":"2020-5-01","lat":47.6647,"lon":102.5479,"sum_rrr":0.3},{"sindex":507,"date":"2020-5-01","lat":48.04631,"lon":100.5057,"sum_rrr":0.0},{"sindex":510,"date":"2020-5-01","lat":47.85949,"lon":99.4396,"sum_rrr":0.0},{"sindex":532,"date":"2020-5-01","lat":49.04058,"lon":89.43118,"sum_rrr":2.2},{"sindex":740,"date":"2020-5-01","lat":43.70446,"lon":105.9663,"sum_rrr":2.2},{"sindex":221,"date":"2020-5-01","lat":49.70049,"lon":96.3633,"sum_rrr":2.0},{"sindex":244,"date":"2020-5-01","lat":49.49024,"lon":105.9398,"sum_rrr":5.7},{"sindex":334,"date":"2020-5-01","lat":45.19382,"lon":100.7772,"sum_rrr":0.0},{"sindex":555,"date":"2020-5-01","lat":45.41408,"lon":100.5717,"sum_rrr":0.0},{"sindex":560,"date":"2020-5-01","lat":46.41897,"lon":100.8455,"sum_rrr":2.7},{"sindex":931,"date":"2020-5-01","lat":49.30897,"lon":105.9239,"sum_rrr":7.2},{"sindex":201,"date":"2020-5-01","lat":49.72886,"lon":93.2702,"sum_rrr":1.5},{"sindex":215,"date":"2020-5-01","lat":49.10479,"lon":91.7262,"sum_rrr":0.0},{"sindex":245,"date":"2020-5-01","lat":48.08544,"lon":104.8064,"sum_rrr":8.4},{"sindex":758,"date":"2020-5-01","lat":47.59698,"lon":112.3506,"sum_rrr":2.0},{"sindex":759,"date":"2020-5-01","lat":46.51008,"lon":112.3544,"sum_rrr":5.2},{"sindex":237,"date":"2020-5-01","lat":48.52905,"lon":101.3679,"sum_rrr":0.0},{"sindex":774,"date":"2020-5-01","lat":50.07146,"lon":105.8738,"sum_rrr":7.3},{"sindex":239,"date":"2020-5-01","lat":48.81687,"lon":103.5171,"sum_rrr":0.7},{"sindex":240,"date":"2020-5-01","lat":50.24301,"lon":106.1727,"sum_rrr":9.0},{"sindex":247,"date":"2020-5-01","lat":48.25865,"lon":105.4042,"sum_rrr":4.0},{"sindex":254,"date":"2020-5-01","lat":49.02225,"lon":111.6117,"sum_rrr":18.8},{"sindex":256,"date":"2020-5-01","lat":49.55091,"lon":114.4042,"sum_rrr":2.2},{"sindex":257,"date":"2020-5-01","lat":48.61608,"lon":110.599,"sum_rrr":10.8},{"sindex":259,"date":"2020-5-01","lat":48.08123,"lon":114.5375,"sum_rrr":0.5},{"sindex":272,"date":"2020-5-01","lat":47.72689,"lon":96.8472,"sum_rrr":0.0},{"sindex":286,"date":"2020-5-01","lat":47.35153,"lon":104.4918,"sum_rrr":0.1},{"sindex":287,"date":"2020-5-01","lat":46.17379,"lon":100.7102,"sum_rrr":4.3},{"sindex":290,"date":"2020-5-01","lat":47.72649,"lon":106.9361,"sum_rrr":0.0},{"sindex":356,"date":"2020-5-01","lat":45.32141,"lon":113.8462,"sum_rrr":1.6},{"sindex":301,"date":"2020-5-01","lat":47.21364,"lon":108.7377,"sum_rrr":1.2},{"sindex":302,"date":"2020-5-01","lat":47.78583,"lon":112.1108,"sum_rrr":53.3},{"sindex":303,"date":"2020-5-01","lat":47.89225,"lon":109.8022,"sum_rrr":9.2},{"sindex":304,"date":"2020-5-01","lat":47.30839,"lon":110.6244,"sum_rrr":1.5},{"sindex":307,"date":"2020-5-01","lat":46.24314,"lon":110.8413,"sum_rrr":0.5},{"sindex":314,"date":"2020-5-01","lat":46.95508,"lon":115.2964,"sum_rrr":6.4},{"sindex":337,"date":"2020-5-01","lat":45.41408,"lon":100.5717,"sum_rrr":0.0},{"sindex":19,"date":"2020-5-01","lat":49.08649,"lon":104.4068,"sum_rrr":7.4},{"sindex":358,"date":"2020-5-01","lat":43.71375,"lon":111.9042,"sum_rrr":1.4},{"sindex":370,"date":"2020-5-01","lat":47.71455,"lon":106.4097,"sum_rrr":0.0},{"sindex":581,"date":"2020-5-01","lat":48.29666,"lon":103.4271,"sum_rrr":0.5},{"sindex":591,"date":"2020-5-01","lat":46.99871,"lon":95.201,"sum_rrr":5.0},{"sindex":596,"date":"2020-5-01","lat":46.71494,"lon":96.5214,"sum_rrr":0.5},{"sindex":597,"date":"2020-5-01","lat":45.83113,"lon":94.1384,"sum_rrr":4.7},{"sindex":598,"date":"2020-5-01","lat":45.92736,"lon":96.1583,"sum_rrr":0.3},{"sindex":603,"date":"2020-5-01","lat":46.27091,"lon":95.267,"sum_rrr":0.8},{"sindex":616,"date":"2020-5-01","lat":45.80107,"lon":109.3175,"sum_rrr":1.2},{"sindex":617,"date":"2020-5-01","lat":45.54482,"lon":110.4688,"sum_rrr":0.6},{"sindex":621,"date":"2020-5-01","lat":44.73051,"lon":110.7822,"sum_rrr":0.5},{"sindex":622,"date":"2020-5-01","lat":44.69405,"lon":109.0168,"sum_rrr":2.0},{"sindex":637,"date":"2020-5-01","lat":48.05374,"lon":114.3605,"sum_rrr":0.3},{"sindex":645,"date":"2020-5-01","lat":49.86676,"lon":115.7007,"sum_rrr":0.0},{"sindex":907,"date":"2020-5-01","lat":48.68986,"lon":110.1694,"sum_rrr":24.7},{"sindex":909,"date":"2020-5-01","lat":46.89922,"lon":109.7566,"sum_rrr":1.5},{"sindex":220,"date":"2020-5-01","lat":48.87058,"lon":96.9616,"sum_rrr":0.0},{"sindex":913,"date":"2020-5-01","lat":47.48686,"lon":109.4733,"sum_rrr":8.6},{"sindex":915,"date":"2020-5-01","lat":48.69164,"lon":111.9872,"sum_rrr":12.8},{"sindex":916,"date":"2020-5-01","lat":47.50781,"lon":110.1835,"sum_rrr":4.6},{"sindex":919,"date":"2020-5-01","lat":48.18472,"lon":110.3228,"sum_rrr":12.3},{"sindex":679,"date":"2020-5-01","lat":48.21171,"lon":97.371,"sum_rrr":0.7},{"sindex":264,"date":"2020-5-01","lat":47.10812,"lon":92.8373,"sum_rrr":2.2},{"sindex":267,"date":"2020-5-01","lat":46.69189,"lon":92.7988,"sum_rrr":4.2},{"sindex":269,"date":"2020-5-01","lat":47.66419,"lon":92.8125,"sum_rrr":1.7},{"sindex":339,"date":"2020-5-01","lat":44.09611,"lon":103.5369,"sum_rrr":4.2},{"sindex":351,"date":"2020-5-01","lat":45.79557,"lon":111.2106,"sum_rrr":3.5},{"sindex":317,"date":"2020-5-01","lat":45.92879,"lon":115.3762,"sum_rrr":6.3},{"sindex":361,"date":"2020-5-01","lat":47.41938,"lon":92.2239,"sum_rrr":0.1},{"sindex":202,"date":"2020-5-01","lat":50.11891,"lon":101.5821,"sum_rrr":4.5},{"sindex":760,"date":"2020-5-01","lat":46.18733,"lon":112.945,"sum_rrr":3.0},{"sindex":534,"date":"2020-5-01","lat":48.26667,"lon":88.86667,"sum_rrr":2.8},{"sindex":222,"date":"2020-5-01","lat":49.52207,"lon":97.73443,"sum_rrr":0.1},{"sindex":235,"date":"2020-5-01","lat":48.28007,"lon":102.98,"sum_rrr":0.6},{"sindex":661,"date":"2020-5-01","lat":46.20867,"lon":106.7147,"sum_rrr":0.0},{"sindex":208,"date":"2020-5-01","lat":50.55216,"lon":101.5153,"sum_rrr":7.9},{"sindex":231,"date":"2020-5-01","lat":49.63856,"lon":100.1668,"sum_rrr":1.5},{"sindex":248,"date":"2020-5-01","lat":47.98866,"lon":107.4566,"sum_rrr":0.0},{"sindex":680,"date":"2020-5-01","lat":48.72238,"lon":98.7955,"sum_rrr":1.1},{"sindex":687,"date":"2020-5-01","lat":49.65192,"lon":95.7737,"sum_rrr":0.3},{"sindex":756,"date":"2020-5-01","lat":46.78681,"lon":113.8771,"sum_rrr":12.2},{"sindex":326,"date":"2020-5-01","lat":45.012,"lon":98.9333,"sum_rrr":0.0},{"sindex":577,"date":"2020-5-01","lat":48.6651,"lon":102.6177,"sum_rrr":3.9},{"sindex":639,"date":"2020-5-01","lat":47.99972,"lon":113.928,"sum_rrr":0.3},{"sindex":688,"date":"2020-5-01","lat":48.51612,"lon":94.2865,"sum_rrr":0.0},{"sindex":784,"date":"2020-5-01","lat":49.67576,"lon":105.821,"sum_rrr":3.1},{"sindex":912,"date":"2020-5-01","lat":47.1815,"lon":109.1904,"sum_rrr":3.2},{"sindex":211,"date":"2020-5-01","lat":50.47844,"lon":93.5995,"sum_rrr":0.4},{"sindex":218,"date":"2020-5-01","lat":47.99591,"lon":91.6324,"sum_rrr":1.6},{"sindex":229,"date":"2020-5-01","lat":48.15685,"lon":99.8767,"sum_rrr":0.0},{"sindex":242,"date":"2020-5-01","lat":49.14363,"lon":105.4021,"sum_rrr":5.9},{"sindex":250,"date":"2020-5-01","lat":48.2057,"lon":108.4862,"sum_rrr":0.1},{"sindex":260,"date":"2020-5-01","lat":47.06539,"lon":91.853,"sum_rrr":1.7},{"sindex":268,"date":"2020-5-01","lat":45.5608,"lon":94.361,"sum_rrr":1.1},{"sindex":281,"date":"2020-5-01","lat":47.3867,"lon":101.9085,"sum_rrr":2.9},{"sindex":284,"date":"2020-5-01","lat":46.70206,"lon":100.1428,"sum_rrr":3.9},{"sindex":288,"date":"2020-5-01","lat":46.25884,"lon":102.789,"sum_rrr":0.2},{"sindex":305,"date":"2020-5-01","lat":46.68969,"lon":113.2865,"sum_rrr":13.0},{"sindex":341,"date":"2020-5-01","lat":45.74304,"lon":106.2642,"sum_rrr":0.0},{"sindex":347,"date":"2020-5-01","lat":44.42319,"lon":105.3168,"sum_rrr":0.5},{"sindex":352,"date":"2020-5-01","lat":45.74858,"lon":112.3561,"sum_rrr":3.9},{"sindex":354,"date":"2020-5-01","lat":44.87807,"lon":110.1192,"sum_rrr":0.0},{"sindex":640,"date":"2020-5-01","lat":49.14508,"lon":114.8757,"sum_rrr":0.3},{"sindex":644,"date":"2020-5-01","lat":48.56809,"lon":113.2369,"sum_rrr":0.4},{"sindex":515,"date":"2020-5-01","lat":47.53926,"lon":100.2317,"sum_rrr":2.0},{"sindex":207,"date":"2020-5-01","lat":50.43858,"lon":100.152,"sum_rrr":2.1},{"sindex":313,"date":"2020-5-01","lat":47.63015,"lon":118.6221,"sum_rrr":18.0},{"sindex":206,"date":"2020-5-01","lat":50.17872,"lon":98.97552,"sum_rrr":1.4},{"sindex":243,"date":"2020-5-01","lat":49.74917,"lon":106.6611,"sum_rrr":2.0},{"sindex":712,"date":"2020-5-01","lat":46.76158,"lon":103.513,"sum_rrr":0.3},{"sindex":779,"date":"2020-5-01","lat":50.32132,"lon":105.0463,"sum_rrr":5.3},{"sindex":854,"date":"2020-5-01","lat":47.52104,"lon":91.625,"sum_rrr":1.1},{"sindex":885,"date":"2020-5-01","lat":49.29153,"lon":100.2515,"sum_rrr":0.1},{"sindex":251,"date":"2020-5-01","lat":49.24459,"lon":106.4118,"sum_rrr":15.4},{"sindex":266,"date":"2020-5-01","lat":46.3128,"lon":93.9018,"sum_rrr":2.3},{"sindex":329,"date":"2020-5-01","lat":44.54559,"lon":99.10551,"sum_rrr":2.1},{"sindex":364,"date":"2020-5-01","lat":48.1261,"lon":91.3734,"sum_rrr":0.7},{"sindex":530,"date":"2020-5-01","lat":48.90704,"lon":89.64449,"sum_rrr":1.8},{"sindex":620,"date":"2020-5-01","lat":46.38191,"lon":110.0969,"sum_rrr":8.5},{"sindex":659,"date":"2020-5-01","lat":45.23949,"lon":104.797,"sum_rrr":0.0},{"sindex":685,"date":"2020-5-01","lat":48.98649,"lon":96.5515,"sum_rrr":0.3},{"sindex":753,"date":"2020-5-01","lat":46.99342,"lon":112.0516,"sum_rrr":3.0},{"sindex":754,"date":"2020-5-01","lat":45.14659,"lon":113.6759,"sum_rrr":2.5},{"sindex":794,"date":"2020-5-01","lat":48.36438,"lon":106.7286,"sum_rrr":4.4},{"sindex":829,"date":"2020-5-01","lat":49.32372,"lon":95.2714,"sum_rrr":0.3},{"sindex":230,"date":"2020-5-01","lat":49.60914,"lon":101.9834,"sum_rrr":0.9},{"sindex":292,"date":"2020-5-01","lat":47.91873,"lon":106.8479,"sum_rrr":1.7},{"sindex":210,"date":"2020-5-01","lat":49.61529,"lon":90.24335,"sum_rrr":0.0},{"sindex":219,"date":"2020-5-01","lat":47.6464,"lon":94.999,"sum_rrr":0.6}]